parte2_capa_transaccion/FSM/testbench/probador.v
module probador #(
    parameter NUM_FIFOS = 8,
    parameter FIFO_DEPTH = 8, // DEBE SER UNA POTENCIA DE 2
    parameter FIFO_WORD_SIZE = 10,
    parameter FIFO_PTR_SIZE = $clog2(FIFO_DEPTH)
) ( 
// Módulo probador: generador de señales y monitor de datos.
// Entradas del monitor de datos
	// Condicional
	input idle,
    input [FIFO_PTR_SIZE-1:0] almost_empty_threshold,
    input [FIFO_PTR_SIZE-1:0] almost_full_threshold,
	// Síntesis
	input idle_synth,
    input [FIFO_PTR_SIZE-1:0] almost_empty_threshold_synth,
    input [FIFO_PTR_SIZE-1:0] almost_full_threshold_synth,
// Salidas del generador de señales
    output reg clk,
    output reg reset_L,
    output reg init,
    output reg [FIFO_PTR_SIZE-1:0] almost_empty_threshold_input,
    output reg [FIFO_PTR_SIZE-1:0] almost_full_threshold_input,
    output reg [NUM_FIFOS-1:0] FIFOs_empty);
	

    integer prob_i; // contador
	// checker
    integer check;
    always @(*) begin
		check = 0;
        if (idle == idle_synth && almost_empty_threshold == almost_empty_threshold_synth && almost_full_threshold == almost_full_threshold_synth) 
            check = 1;    
        else
            check = 0;    
    end 

    // Reloj
	initial	clk <= 0;			// Valor inicial al reloj, sino siempre será indeterminado
	always #10 clk <= ~clk;		// Hace "toggle" cada 2*1ns

	// Bloque de procedimiento, no sintetizable, se recorre una única vez.
	// Generalmente, los initial sólo se usan en los testbench o probadores.
	// Se recomienda siempre sincronizar con el reloj y utilizar asignaciones no bloqueantes en la generación de señales.
	initial begin
		$dumpfile("testbench/FSM_sim.vcd");	// Nombre de archivo del "dump"
		$dumpvars;              // Directiva para "dumpear" variables
		// Mensaje que se imprime en consola una vez
		$display ("\t\ttime\tclk,\tcheck");
		// Mensaje que se imprime en consola cada vez que un elemento de la lista cambia
		$monitor($time,"\t%b%d", clk, check);
        
		// ** MODIFICAR A PARTIR DE ACÁ
        // Inicialización de datos
		reset_L = 0;
		init = 0;
		almost_empty_threshold_input = 0;
		almost_full_threshold_input = 0;
		FIFOs_empty = 'hFF;

		@(posedge clk) begin
			reset_L <= 1;
			init <= 1;
			almost_empty_threshold_input <= 3;
			almost_full_threshold_input <= 5;
		end

		@(posedge clk)

		@(posedge clk) begin
			almost_empty_threshold_input <= 2;
			almost_full_threshold_input <= 6;
		end

		@(posedge clk) begin
			init <= 0;
			almost_empty_threshold_input <= 1;
			almost_full_threshold_input <= 7;
			FIFOs_empty <= 'hFE;
		end

		@(posedge clk) begin
			FIFOs_empty <= 'hFD;
		end

		@(posedge clk) begin
			FIFOs_empty <= 'hFE;
		end

		@(posedge clk) begin
			FIFOs_empty <= 'hFF;
		end

		@(posedge clk) begin
			FIFOs_empty <= 'hFF;
		end

		@(posedge clk)
		// Final de pruebas

		$finish; // Termina de almacenar señales
	end
endmodule

parte2_capa_transaccion/FSM/synthesis/FSM_synth.v
/* Generated by Yosys 0.9 (git sha1 UNKNOWN, clang 6.0.0-1ubuntu2 -fPIC -Os) */

(* dynports =  1  *)
(* top =  1  *)
(* src = "rtl/FSM.v:1" *)
module FSM_synth(clk, reset_L, init, almost_empty_threshold_input, almost_full_threshold_input, FIFOs_empty, idle, almost_empty_threshold, almost_full_threshold);
  wire _00_;
  wire _01_;
  wire _02_;
  wire _03_;
  wire _04_;
  wire _05_;
  wire _06_;
  wire _07_;
  wire _08_;
  wire _09_;
  wire _10_;
  wire _11_;
  wire _12_;
  wire _13_;
  wire _14_;
  wire _15_;
  wire _16_;
  wire _17_;
  wire _18_;
  wire _19_;
  (* src = "rtl/FSM.v:12" *)
  input [7:0] FIFOs_empty;
  (* src = "rtl/FSM.v:14" *)
  output [2:0] almost_empty_threshold;
  (* src = "rtl/FSM.v:10" *)
  input [2:0] almost_empty_threshold_input;
  (* src = "rtl/FSM.v:15" *)
  output [2:0] almost_full_threshold;
  (* src = "rtl/FSM.v:11" *)
  input [2:0] almost_full_threshold_input;
  (* src = "rtl/FSM.v:7" *)
  input clk;
  (* onehot = 32'd1 *)
  wire [3:0] estado_actual;
  (* src = "rtl/FSM.v:13" *)
  output idle;
  (* src = "rtl/FSM.v:9" *)
  input init;
  (* src = "rtl/FSM.v:8" *)
  input reset_L;
  NOT _20_ (
    .A(reset_L),
    .Y(_01_)
  );
  NOT _21_ (
    .A(estado_actual[3]),
    .Y(_04_)
  );
  NAND _22_ (
    .A(FIFOs_empty[5]),
    .B(FIFOs_empty[4]),
    .Y(_05_)
  );
  NAND _23_ (
    .A(FIFOs_empty[7]),
    .B(FIFOs_empty[6]),
    .Y(_06_)
  );
  NOR _24_ (
    .A(_05_),
    .B(_06_),
    .Y(_07_)
  );
  NAND _25_ (
    .A(FIFOs_empty[1]),
    .B(FIFOs_empty[0]),
    .Y(_08_)
  );
  NAND _26_ (
    .A(FIFOs_empty[3]),
    .B(FIFOs_empty[2]),
    .Y(_09_)
  );
  NOR _27_ (
    .A(_08_),
    .B(_09_),
    .Y(_10_)
  );
  NAND _28_ (
    .A(_07_),
    .B(_10_),
    .Y(_11_)
  );
  NOR _29_ (
    .A(estado_actual[2]),
    .B(estado_actual[1]),
    .Y(_12_)
  );
  NAND _30_ (
    .A(reset_L),
    .B(_11_),
    .Y(_13_)
  );
  NOR _31_ (
    .A(_12_),
    .B(_13_),
    .Y(_00_)
  );
  NOR _32_ (
    .A(init),
    .B(_04_),
    .Y(_14_)
  );
  NOR _33_ (
    .A(_11_),
    .B(_12_),
    .Y(_15_)
  );
  NOR _34_ (
    .A(_14_),
    .B(_15_),
    .Y(_16_)
  );
  NOR _35_ (
    .A(_01_),
    .B(_16_),
    .Y(_02_)
  );
  NAND _36_ (
    .A(init),
    .B(estado_actual[3]),
    .Y(_17_)
  );
  NOT _37_ (
    .A(_17_),
    .Y(_18_)
  );
  NOR _38_ (
    .A(estado_actual[0]),
    .B(_18_),
    .Y(_19_)
  );
  NOR _39_ (
    .A(_01_),
    .B(_19_),
    .Y(_03_)
  );
  NAND _40_ (
    .A(estado_actual[2]),
    .B(_11_),
    .Y(idle)
  );
  DFF _41_ (
    .C(clk),
    .D(_01_),
    .Q(estado_actual[0])
  );
  DFF _42_ (
    .C(clk),
    .D(_00_),
    .Q(estado_actual[1])
  );
  DFF _43_ (
    .C(clk),
    .D(_02_),
    .Q(estado_actual[2])
  );
  DFF _44_ (
    .C(clk),
    .D(_03_),
    .Q(estado_actual[3])
  );
  assign almost_empty_threshold = 3'h2;
  assign almost_full_threshold = 3'h6;
endmodule

parte2_capa_transaccion/Transaccion/rtl/FSM.v
module FSM #(
    parameter NUM_FIFOS = 8,
    parameter FIFO_DEPTH = 8, // DEBE SER UNA POTENCIA DE 2
    parameter FIFO_WORD_SIZE = 10,
    parameter FIFO_PTR_SIZE = $clog2(FIFO_DEPTH)
)(
    input clk,
    input reset_L,
    input init,
    input [FIFO_PTR_SIZE-1:0] almost_empty_threshold_input,
    input [FIFO_PTR_SIZE-1:0] almost_full_threshold_input,
    input [NUM_FIFOS-1:0] FIFOs_empty,
    output reg idle,
    output reg [FIFO_PTR_SIZE-1:0] almost_empty_threshold,
    output reg [FIFO_PTR_SIZE-1:0] almost_full_threshold);

    // Máquina de estados finita
    reg [16:0] estado_actual, proximo_estado; // estados actual y próximo

    // Estados:
    parameter RESET = 1; // codificado one-hot
    parameter INIT = 2;
    parameter IDLE = 4;
    parameter ACTIVE = 8;

    always @(posedge clk) begin // condición de reset
        if(~reset_L) begin
            estado_actual <= RESET;
            almost_empty_threshold <= 2;
            almost_full_threshold <= 6;
        end

        else begin
            estado_actual <= proximo_estado; // Flops de estado de FSM
        end
    end

    always @(*) begin // Lógica de estado próximo
        proximo_estado = estado_actual;
        idle = 0;

        case(estado_actual) 
            RESET: // 1
            begin
                if(reset_L)
                    proximo_estado = INIT;
                else
                    proximo_estado = RESET;
            end 

            INIT: // 2
            begin
                if(init) begin
                    proximo_estado = INIT;
                    almost_empty_threshold = almost_empty_threshold_input;
                    almost_full_threshold = almost_full_threshold_input;
                end

                else 
                    proximo_estado = IDLE;
            end

            IDLE: // 4
            begin
                if(&FIFOs_empty) begin
                    idle = 1;
                    proximo_estado = IDLE;
                end
                    
                else  begin
                    idle = 0;
                    proximo_estado = ACTIVE;
                end
            end

            ACTIVE: // 8
            begin
                if(&FIFOs_empty)
                    proximo_estado = IDLE;
                else
                    proximo_estado = ACTIVE;
            end

        endcase
    end
    
endmodule

parte2_capa_transaccion/Transaccion/testbench/testbench.v
`include "synthesis/cmos_cells/cmos_cells.v"
`include "rtl/FSM.v"
`include "synthesis/FSM_synth.v"
`include "testbench/probador.v"

`timescale 	1ns/100ps // escala	unidad temporal (valor de "#1") / precisión

module testbench; // Testbench

    parameter NUM_FIFOS = 8;
    parameter FIFO_DEPTH = 8; // DEBE SER UNA POTENCIA DE 2
    parameter FIFO_WORD_SIZE = 10;
    parameter FIFO_PTR_SIZE = $clog2(FIFO_DEPTH);

	/*AUTOWIRE*/
	// Beginning of automatic wires (for undeclared instantiated-module outputs)
	wire [NUM_FIFOS-1:0] FIFOs_empty;	// From probador_0 of probador.v
	wire [FIFO_PTR_SIZE-1:0] almost_empty_threshold;// From FSM_0 of FSM.v
	wire [FIFO_PTR_SIZE-1:0] almost_empty_threshold_input;// From probador_0 of probador.v
	wire [2:0]	almost_empty_threshold_synth;// From FSM_0_synth of FSM_synth.v
	wire [FIFO_PTR_SIZE-1:0] almost_full_threshold;// From FSM_0 of FSM.v
	wire [FIFO_PTR_SIZE-1:0] almost_full_threshold_input;// From probador_0 of probador.v
	wire [2:0]	almost_full_threshold_synth;// From FSM_0_synth of FSM_synth.v
	wire		clk;			// From probador_0 of probador.v
	wire		idle;			// From FSM_0 of FSM.v
	wire		idle_synth;		// From FSM_0_synth of FSM_synth.v
	wire		init;			// From probador_0 of probador.v
	wire		reset_L;		// From probador_0 of probador.v
	// End of automatics

	// Descripción conductual
	FSM FSM_0 (	
		/*AUTOINST*/
		   // Outputs
		   .idle		(idle),
		   .almost_empty_threshold(almost_empty_threshold[FIFO_PTR_SIZE-1:0]),
		   .almost_full_threshold(almost_full_threshold[FIFO_PTR_SIZE-1:0]),
		   // Inputs
		   .clk			(clk),
		   .reset_L		(reset_L),
		   .init		(init),
		   .almost_empty_threshold_input(almost_empty_threshold_input[FIFO_PTR_SIZE-1:0]),
		   .almost_full_threshold_input(almost_full_threshold_input[FIFO_PTR_SIZE-1:0]),
		   .FIFOs_empty		(FIFOs_empty[NUM_FIFOS-1:0]));
	
	// Descripción estructural
	/*FSM_synth AUTO_TEMPLATE (
				   .almost_empty_threshold(almost_empty_threshold_synth[2:0]),
			       .almost_full_threshold	(almost_full_threshold_synth[2:0]),
			       .idle		(idle_synth),
			);*/
	FSM_synth FSM_0_synth (
		/*AUTOINST*/
			       // Outputs
			       .almost_empty_threshold(almost_empty_threshold_synth[2:0]), // Templated
			       .almost_full_threshold(almost_full_threshold_synth[2:0]), // Templated
			       .idle		(idle_synth),	 // Templated
			       // Inputs
			       .FIFOs_empty	(FIFOs_empty[7:0]),
			       .almost_empty_threshold_input(almost_empty_threshold_input[2:0]),
			       .almost_full_threshold_input(almost_full_threshold_input[2:0]),
			       .clk		(clk),
			       .init		(init),
			       .reset_L		(reset_L));

	// Probador: generador de señales y monitor
	probador probador_0(
		/*AUTOINST*/
			    // Outputs
			    .clk		(clk),
			    .reset_L		(reset_L),
			    .init		(init),
			    .almost_empty_threshold_input(almost_empty_threshold_input[FIFO_PTR_SIZE-1:0]),
			    .almost_full_threshold_input(almost_full_threshold_input[FIFO_PTR_SIZE-1:0]),
			    .FIFOs_empty	(FIFOs_empty[NUM_FIFOS-1:0]),
			    // Inputs
			    .idle		(idle),
			    .almost_empty_threshold(almost_empty_threshold[FIFO_PTR_SIZE-1:0]),
			    .almost_full_threshold(almost_full_threshold[FIFO_PTR_SIZE-1:0]),
			    .idle_synth		(idle_synth),
			    .almost_empty_threshold_synth(almost_empty_threshold_synth[FIFO_PTR_SIZE-1:0]),
			    .almost_full_threshold_synth(almost_full_threshold_synth[FIFO_PTR_SIZE-1:0]));
endmodule

// Local Variables:
// verilog-library-directories:("." "../rtl/" "../synthesis/")
// End:

parte2_capa_transaccion/Memoria/cmos_cells.v
module BUF(A, Y);
input A;
output Y;
assign Y = A;
endmodule

module NOT(A, Y);
input A;
output Y;
assign Y = ~A;
endmodule

module NAND(A, B, Y);
input A, B;
output Y;
assign Y = ~(A & B);
endmodule

module NOR(A, B, Y);
input A, B;
output Y;
assign Y = ~(A | B);
endmodule

module DFF(C, D, Q);
input C, D;
output reg Q;
always @(posedge C)
	Q <= D;
endmodule

module DFFSR(C, D, Q, S, R);
input C, D, S, R;
output reg Q;
always @(posedge C, posedge S, posedge R)
	if (S)
		Q <= 1'b1;
	else if (R)
		Q <= 1'b0;
	else
		Q <= D;
endmodule

parte2_capa_transaccion/FSM/testbench/FSM_sim.vcd
$date
	Mon Jul 12 20:35:07 2021
$end
$version
	Icarus Verilog
$end
$timescale
	100ps
$end
$scope module BUF $end
$var wire 1 ! A $end
$var wire 1 " Y $end
$upscope $end
$scope module DFFSR $end
$var wire 1 # C $end
$var wire 1 $ D $end
$var wire 1 % R $end
$var wire 1 & S $end
$var reg 1 ' Q $end
$upscope $end
$scope module testbench $end
$var wire 3 ( almost_empty_threshold_synth [2:0] $end
$var wire 3 ) almost_full_threshold_synth [2:0] $end
$var wire 1 * reset_L $end
$var wire 1 + init $end
$var wire 1 , idle_synth $end
$var wire 1 - idle $end
$var wire 1 . clk $end
$var wire 3 / almost_full_threshold_input [2:0] $end
$var wire 3 0 almost_full_threshold [2:0] $end
$var wire 3 1 almost_empty_threshold_input [2:0] $end
$var wire 3 2 almost_empty_threshold [2:0] $end
$var wire 8 3 FIFOs_empty [7:0] $end
$scope module FSM_0 $end
$var wire 1 * reset_L $end
$var wire 1 + init $end
$var wire 1 . clk $end
$var wire 3 4 almost_full_threshold_input [2:0] $end
$var wire 3 5 almost_empty_threshold_input [2:0] $end
$var wire 8 6 FIFOs_empty [7:0] $end
$var reg 3 7 almost_empty_threshold [2:0] $end
$var reg 3 8 almost_full_threshold [2:0] $end
$var reg 17 9 estado_actual [16:0] $end
$var reg 1 - idle $end
$var reg 17 : proximo_estado [16:0] $end
$upscope $end
$scope module FSM_0_synth $end
$var wire 3 ; almost_empty_threshold [2:0] $end
$var wire 3 < almost_full_threshold [2:0] $end
$var wire 1 * reset_L $end
$var wire 1 + init $end
$var wire 1 , idle $end
$var wire 4 = estado_actual [3:0] $end
$var wire 1 . clk $end
$var wire 3 > almost_full_threshold_input [2:0] $end
$var wire 3 ? almost_empty_threshold_input [2:0] $end
$var wire 1 @ _19_ $end
$var wire 1 A _18_ $end
$var wire 1 B _17_ $end
$var wire 1 C _16_ $end
$var wire 1 D _15_ $end
$var wire 1 E _14_ $end
$var wire 1 F _13_ $end
$var wire 1 G _12_ $end
$var wire 1 H _11_ $end
$var wire 1 I _10_ $end
$var wire 1 J _09_ $end
$var wire 1 K _08_ $end
$var wire 1 L _07_ $end
$var wire 1 M _06_ $end
$var wire 1 N _05_ $end
$var wire 1 O _04_ $end
$var wire 1 P _03_ $end
$var wire 1 Q _02_ $end
$var wire 1 R _01_ $end
$var wire 1 S _00_ $end
$var wire 8 T FIFOs_empty [7:0] $end
$scope module _20_ $end
$var wire 1 R Y $end
$var wire 1 * A $end
$upscope $end
$scope module _21_ $end
$var wire 1 U A $end
$var wire 1 O Y $end
$upscope $end
$scope module _22_ $end
$var wire 1 V A $end
$var wire 1 W B $end
$var wire 1 N Y $end
$upscope $end
$scope module _23_ $end
$var wire 1 X A $end
$var wire 1 Y B $end
$var wire 1 M Y $end
$upscope $end
$scope module _24_ $end
$var wire 1 N A $end
$var wire 1 M B $end
$var wire 1 L Y $end
$upscope $end
$scope module _25_ $end
$var wire 1 Z A $end
$var wire 1 [ B $end
$var wire 1 K Y $end
$upscope $end
$scope module _26_ $end
$var wire 1 \ A $end
$var wire 1 ] B $end
$var wire 1 J Y $end
$upscope $end
$scope module _27_ $end
$var wire 1 K A $end
$var wire 1 J B $end
$var wire 1 I Y $end
$upscope $end
$scope module _28_ $end
$var wire 1 L A $end
$var wire 1 I B $end
$var wire 1 H Y $end
$upscope $end
$scope module _29_ $end
$var wire 1 ^ A $end
$var wire 1 _ B $end
$var wire 1 G Y $end
$upscope $end
$scope module _30_ $end
$var wire 1 H B $end
$var wire 1 F Y $end
$var wire 1 * A $end
$upscope $end
$scope module _31_ $end
$var wire 1 G A $end
$var wire 1 F B $end
$var wire 1 S Y $end
$upscope $end
$scope module _32_ $end
$var wire 1 O B $end
$var wire 1 E Y $end
$var wire 1 + A $end
$upscope $end
$scope module _33_ $end
$var wire 1 H A $end
$var wire 1 G B $end
$var wire 1 D Y $end
$upscope $end
$scope module _34_ $end
$var wire 1 E A $end
$var wire 1 D B $end
$var wire 1 C Y $end
$upscope $end
$scope module _35_ $end
$var wire 1 R A $end
$var wire 1 C B $end
$var wire 1 Q Y $end
$upscope $end
$scope module _36_ $end
$var wire 1 ` B $end
$var wire 1 B Y $end
$var wire 1 + A $end
$upscope $end
$scope module _37_ $end
$var wire 1 B A $end
$var wire 1 A Y $end
$upscope $end
$scope module _38_ $end
$var wire 1 a A $end
$var wire 1 A B $end
$var wire 1 @ Y $end
$upscope $end
$scope module _39_ $end
$var wire 1 R A $end
$var wire 1 @ B $end
$var wire 1 P Y $end
$upscope $end
$scope module _40_ $end
$var wire 1 b A $end
$var wire 1 H B $end
$var wire 1 , Y $end
$upscope $end
$scope module _41_ $end
$var wire 1 R D $end
$var wire 1 . C $end
$var reg 1 c Q $end
$upscope $end
$scope module _42_ $end
$var wire 1 S D $end
$var wire 1 . C $end
$var reg 1 d Q $end
$upscope $end
$scope module _43_ $end
$var wire 1 Q D $end
$var wire 1 . C $end
$var reg 1 e Q $end
$upscope $end
$scope module _44_ $end
$var wire 1 P D $end
$var wire 1 . C $end
$var reg 1 f Q $end
$upscope $end
$upscope $end
$scope module probador_0 $end
$var wire 3 g almost_empty_threshold [2:0] $end
$var wire 3 h almost_empty_threshold_synth [2:0] $end
$var wire 3 i almost_full_threshold [2:0] $end
$var wire 3 j almost_full_threshold_synth [2:0] $end
$var wire 1 - idle $end
$var wire 1 , idle_synth $end
$var reg 8 k FIFOs_empty [7:0] $end
$var reg 3 l almost_empty_threshold_input [2:0] $end
$var reg 3 m almost_full_threshold_input [2:0] $end
$var reg 1 . clk $end
$var reg 1 + init $end
$var reg 1 * reset_L $end
$var integer 32 n check [31:0] $end
$upscope $end
$upscope $end
$enddefinitions $end
#0
$dumpvars
b0 n
b0 m
b0 l
b11111111 k
b110 j
bx i
b10 h
bx g
xf
xe
xd
xc
xb
xa
x`
x_
x^
1]
1\
1[
1Z
1Y
1X
1W
1V
xU
b11111111 T
0S
1R
0Q
0P
xO
0N
0M
1L
0K
0J
1I
0H
xG
1F
xE
xD
xC
1B
0A
x@
b0 ?
b0 >
bx =
b110 <
b10 ;
bx :
bx 9
bx 8
bx 7
b11111111 6
b0 5
b0 4
b11111111 3
bx 2
b0 1
bx 0
b0 /
0.
1-
1,
0+
0*
b110 )
b10 (
x'
z&
z%
z$
z#
z"
z!
$end
#100000000000
1C
0D
0@
1G
0A
0Q
1P
1O
1B
0E
b1 n
1a
0_
0b
0^
0`
0U
0R
b10 :
b110 0
b110 8
b110 i
b10 2
b10 7
b10 g
b1 9
1c
0d
0e
b1 =
0f
b101 /
b101 4
b101 >
b101 m
b11 1
b11 5
b11 ?
b11 l
1+
1*
1.
#200000000000
0.
#300000000000
1P
1A
0B
0@
0O
b0 n
1`
1U
0a
b101 0
b101 8
b101 i
b11 2
b11 7
b11 g
1f
b1000 =
0c
b10 9
1.
#400000000000
0.
#500000000000
b1 n
b110 0
b110 8
b110 i
b10 2
b10 7
b10 g
b110 /
b110 4
b110 >
b110 m
b10 1
b10 5
b10 ?
b10 l
1.
#600000000000
0.
#700000000000
0F
1H
0P
1Q
0I
1@
0C
1K
0A
1B
1E
0[
b100 :
b11111110 3
b11111110 6
b11111110 T
b11111110 k
b111 /
b111 4
b111 >
b111 m
b1 1
b1 5
b1 ?
b1 l
0+
1.
#800000000000
0.
#900000000000
0Q
1C
1S
0E
0,
0G
1O
b1 n
1b
1^
0`
0U
1[
0Z
b1000 :
0-
b100 9
1e
b100 =
0f
b11111101 3
b11111101 6
b11111101 T
b11111101 k
1.
#1000000000000
0.
#1100000000000
1,
b1 n
0[
1Z
0b
0^
1_
1-
b11111110 3
b11111110 6
b11111110 T
b11111110 k
0e
b10 =
1d
b1000 9
1.
#1200000000000
0.
#1300000000000
1Q
0S
0C
1F
1D
0H
1I
0K
1[
b100 :
b11111111 3
b11111111 6
b11111111 T
b11111111 k
1.
#1400000000000
0.
#1500000000000
1b
1^
0_
1e
b100 =
0d
b100 9
1.
