parte1_capa_fisica/phy_tx/paralelo_serial/probador.v
module probador(
		output reg 	 clk_4f,
		output reg 	 clk_32f,
		output reg [7:0] data_in,
		output reg 	 valid_in,
	        output reg 	 reset_L,
		input 		 data_out_cond,
		input 		 data_out_synth);
   
   

   
   //Reloj 4f

   initial clk_4f <= 1;
   always #8 clk_4f <= ~clk_4f;

   //Reloj 32f

   initial clk_32f <= 1;
   always #1 clk_32f <= ~clk_32f;

   //Checker
   integer check = 0;
    always @(*) begin
        if (data_out_cond == data_out_synth) 
            check <= 1;    
        else
            check <= 0;    
    end 
   
   // Secuencia de prueba

   initial
     begin
	$dumpfile ("senales_paralelo_serial.vcd");
	$dumpvars;

	valid_in = 1;
	reset_L = 0;
	@ (posedge clk_4f);

	{data_in} <= {8'hCC};
	

       	@ (posedge clk_4f);
	
      
	{data_in} <= {8'hAA};
	{reset_L} <= 1;
	

	@ (posedge clk_4f);
	
        {valid_in} <= 0;
	{data_in} <= {8'hDD};

	@ (posedge clk_4f);

	{valid_in} <= 1;
	{data_in} <= {8'hFF};

	@ (posedge clk_4f);

	{data_in} <= {8'hEE};

	@ (posedge clk_4f);
	

	$finish;

     end // initial begin
endmodule // probador

parte1_capa_fisica/phy_tx/paralelo_serial/paralelo_serial_synth.v
/* Generated by Yosys 0.9 (git sha1 1979e0b) */

(* top =  1  *)
(* src = "paralelo_serial.v:1" *)
module paralelo_serial_synth(data_out, reset_L, clk_32f, data_in, valid_in);
  (* src = "paralelo_serial.v:15" *)
  wire [2:0] _00_;
  wire _01_;
  wire _02_;
  wire _03_;
  wire _04_;
  wire _05_;
  wire _06_;
  wire _07_;
  wire _08_;
  wire _09_;
  wire _10_;
  wire _11_;
  wire _12_;
  wire _13_;
  wire _14_;
  wire _15_;
  wire _16_;
  wire _17_;
  wire _18_;
  wire _19_;
  wire _20_;
  wire _21_;
  wire _22_;
  wire _23_;
  wire _24_;
  wire _25_;
  wire _26_;
  wire _27_;
  wire _28_;
  wire _29_;
  wire _30_;
  wire _31_;
  wire _32_;
  wire _33_;
  wire _34_;
  wire _35_;
  wire _36_;
  wire _37_;
  wire _38_;
  wire _39_;
  wire _40_;
  wire _41_;
  (* src = "paralelo_serial.v:4" *)
  input clk_32f;
  (* src = "paralelo_serial.v:5" *)
  input [7:0] data_in;
  (* src = "paralelo_serial.v:2" *)
  output data_out;
  (* src = "paralelo_serial.v:8" *)
  wire [2:0] index;
  (* src = "paralelo_serial.v:3" *)
  input reset_L;
  (* src = "paralelo_serial.v:6" *)
  input valid_in;
  NOT _42_ (
    .A(valid_in),
    .Y(_01_)
  );
  NOT _43_ (
    .A(data_in[5]),
    .Y(_02_)
  );
  NOT _44_ (
    .A(reset_L),
    .Y(_03_)
  );
  NOT _45_ (
    .A(index[1]),
    .Y(_04_)
  );
  NOT _46_ (
    .A(index[2]),
    .Y(_05_)
  );
  NOR _47_ (
    .A(_03_),
    .B(index[0]),
    .Y(_00_[0])
  );
  NAND _48_ (
    .A(index[0]),
    .B(index[1]),
    .Y(_06_)
  );
  NOT _49_ (
    .A(_06_),
    .Y(_07_)
  );
  NOR _50_ (
    .A(index[0]),
    .B(index[1]),
    .Y(_08_)
  );
  NOT _51_ (
    .A(_08_),
    .Y(_09_)
  );
  NAND _52_ (
    .A(reset_L),
    .B(_09_),
    .Y(_10_)
  );
  NOR _53_ (
    .A(_07_),
    .B(_10_),
    .Y(_00_[1])
  );
  NOR _54_ (
    .A(_05_),
    .B(_06_),
    .Y(_11_)
  );
  NAND _55_ (
    .A(_05_),
    .B(_06_),
    .Y(_12_)
  );
  NAND _56_ (
    .A(reset_L),
    .B(_12_),
    .Y(_13_)
  );
  NOR _57_ (
    .A(_11_),
    .B(_13_),
    .Y(_00_[2])
  );
  NOR _58_ (
    .A(_01_),
    .B(index[2]),
    .Y(_14_)
  );
  NOR _59_ (
    .A(data_in[4]),
    .B(_06_),
    .Y(_15_)
  );
  NAND _60_ (
    .A(_14_),
    .B(_15_),
    .Y(_16_)
  );
  NAND _61_ (
    .A(reset_L),
    .B(_16_),
    .Y(_17_)
  );
  NOT _62_ (
    .A(_17_),
    .Y(_18_)
  );
  NAND _63_ (
    .A(valid_in),
    .B(_08_),
    .Y(_19_)
  );
  NAND _64_ (
    .A(data_in[7]),
    .B(_05_),
    .Y(_20_)
  );
  NAND _65_ (
    .A(data_in[3]),
    .B(index[2]),
    .Y(_21_)
  );
  NAND _66_ (
    .A(_20_),
    .B(_21_),
    .Y(_22_)
  );
  NOR _67_ (
    .A(_19_),
    .B(_22_),
    .Y(_23_)
  );
  NAND _68_ (
    .A(data_in[0]),
    .B(valid_in),
    .Y(_24_)
  );
  NAND _69_ (
    .A(_11_),
    .B(_24_),
    .Y(_25_)
  );
  NOT _70_ (
    .A(_25_),
    .Y(_26_)
  );
  NOR _71_ (
    .A(_23_),
    .B(_26_),
    .Y(_27_)
  );
  NAND _72_ (
    .A(_18_),
    .B(_27_),
    .Y(_28_)
  );
  NAND _73_ (
    .A(data_in[6]),
    .B(_14_),
    .Y(_29_)
  );
  NAND _74_ (
    .A(index[0]),
    .B(_04_),
    .Y(_30_)
  );
  NOR _75_ (
    .A(_01_),
    .B(data_in[2]),
    .Y(_31_)
  );
  NOR _76_ (
    .A(_05_),
    .B(_31_),
    .Y(_32_)
  );
  NOR _77_ (
    .A(_30_),
    .B(_32_),
    .Y(_33_)
  );
  NAND _78_ (
    .A(_29_),
    .B(_33_),
    .Y(_34_)
  );
  NAND _79_ (
    .A(_02_),
    .B(_14_),
    .Y(_35_)
  );
  NAND _80_ (
    .A(valid_in),
    .B(data_in[1]),
    .Y(_36_)
  );
  NAND _81_ (
    .A(index[2]),
    .B(_36_),
    .Y(_37_)
  );
  NAND _82_ (
    .A(_35_),
    .B(_37_),
    .Y(_38_)
  );
  NOR _83_ (
    .A(index[0]),
    .B(_04_),
    .Y(_39_)
  );
  NAND _84_ (
    .A(_38_),
    .B(_39_),
    .Y(_40_)
  );
  NAND _85_ (
    .A(_34_),
    .B(_40_),
    .Y(_41_)
  );
  NOR _86_ (
    .A(_28_),
    .B(_41_),
    .Y(data_out)
  );
  (* src = "paralelo_serial.v:15" *)
  DFF _87_ (
    .C(clk_32f),
    .D(_00_[0]),
    .Q(index[0])
  );
  (* src = "paralelo_serial.v:15" *)
  DFF _88_ (
    .C(clk_32f),
    .D(_00_[1]),
    .Q(index[1])
  );
  (* src = "paralelo_serial.v:15" *)
  DFF _89_ (
    .C(clk_32f),
    .D(_00_[2]),
    .Q(index[2])
  );
endmodule

parte1_capa_fisica/phy_tx/paralelo_serial/paralelo_serial.v
module paralelo_serial (
			output reg  data_out,
			input 	    reset_L,
			input 	    clk_32f,
			input [7:0] data_in,
			input 	    valid_in);
   
   reg [2:0] 				 index = 000;
   reg [7:0] 				 data2send;
   
  
   

//Lógica de index
 always @ (posedge clk_32f)
   begin
      
      if (~reset_L)
	index <= 000;
      else
	begin
	   if(index <7)
	     index <= index +1;
	   else
	     index <= 0;
	end
   end // always @ (posedge clk_32f)
   



//Lógica de la salida

 always @ (*)
   begin
      if (valid_in)
	data2send = data_in;
      else
	data2send = 8'hBC;
      if (~reset_L)
	data_out <= 0;
      else
	data_out <= data2send[7-index];
   end // always @ (*)
    

endmodule // paralelo_serial

phy_tx/paralelo_serial/Banco_pruebas.v
`timescale 1ns / 100ps
`include "cmos_cells.v"
`include "paralelo_serial.v"
`include "probador.v"
`include "paralelo_serial_synth.v"


module Banco_pruebas ;
   //Cables

   /*AUTOWIRE*/
   // Beginning of automatic wires (for undeclared instantiated-module outputs)
   wire			clk_32f;		// From probador of probador.v
   wire			clk_4f;			// From probador of probador.v
   wire [7:0]		data_in;		// From probador of probador.v
   wire			data_out_cond;		// From paralelo_serial of paralelo_serial.v
   wire			data_out_synth;		// From paralelo_serial_synth of paralelo_serial_synth.v
   wire			reset_L;		// From probador of probador.v
   wire			valid_in;		// From probador of probador.v
   // End of automatics


   //Instancia descripción conductual

   /* paralelo_serial AUTO_TEMPLATE (
   .data_out (data_out_cond));
    */
   
   paralelo_serial paralelo_serial(/*AUTOINST*/
				   // Outputs
				   .data_out		(data_out_cond), // Templated
				   // Inputs
				   .reset_L		(reset_L),
				   .clk_32f		(clk_32f),
				   .data_in		(data_in[7:0]),
				   .valid_in		(valid_in));

   //Instancia descripción estructural

   /* paralelo_serial_synth AUTO_TEMPLATE (
   .data_out (data_out_synth));
    */

   paralelo_serial_synth paralelo_serial_synth (/*AUTOINST*/
						// Outputs
						.data_out	(data_out_synth), // Templated
						// Inputs
						.clk_32f	(clk_32f),
						.data_in	(data_in[7:0]),
						.reset_L	(reset_L),
						.valid_in	(valid_in));
   



   //Instancia probador

   probador probador(/*AUTOINST*/
		     // Outputs
		     .clk_4f		(clk_4f),
		     .clk_32f		(clk_32f),
		     .data_in		(data_in[7:0]),
		     .valid_in		(valid_in),
		     .reset_L		(reset_L),
		     // Inputs
		     .data_out_cond	(data_out_cond),
		     .data_out_synth	(data_out_synth));



endmodule // Banco_pruebas

phy_tx/cmos_cells.v
module BUF(A, Y);
input A;
output Y;
assign Y = A;
endmodule

module NOT(A, Y);
input A;
output Y;
assign  Y = ~A;
endmodule

module NAND(A, B, Y);
input A, B;
output Y;
assign  Y = ~(A & B);
endmodule

module NOR(A, B, Y);
input A, B;
output Y;
assign  Y = ~(A | B);
endmodule

module DFF(C, D, Q);
input C, D;
output reg Q;
always @(posedge C)
	Q <= D;
endmodule

module DFFSR(C, D, Q, S, R);
input C, D, S, R;
output reg Q;
always @(posedge C, posedge S, posedge R)
	if (S)
		Q <= 1'b1;
	else if (R)
		Q <= 1'b0;
	else
		Q <= D;
endmodule

parte1_capa_fisica/phy_tx/paralelo_serial/senales_paralelo_serial.vcd
$date
	Tue Jun 29 16:29:04 2021
$end
$version
	Icarus Verilog
$end
$timescale
	100ps
$end
$scope module BUF $end
$var wire 1 ! A $end
$var wire 1 " Y $end
$upscope $end
$scope module Banco_pruebas $end
$var wire 1 # valid_in $end
$var wire 1 $ reset_L $end
$var wire 1 % data_out_synth $end
$var wire 1 & data_out_cond $end
$var wire 8 ' data_in [7:0] $end
$var wire 1 ( clk_4f $end
$var wire 1 ) clk_32f $end
$scope module paralelo_serial $end
$var wire 1 # valid_in $end
$var wire 1 $ reset_L $end
$var wire 8 * data_in [7:0] $end
$var wire 1 ) clk_32f $end
$var reg 8 + data2send [7:0] $end
$var reg 1 & data_out $end
$var reg 3 , index [2:0] $end
$upscope $end
$scope module paralelo_serial_synth $end
$var wire 1 # valid_in $end
$var wire 1 $ reset_L $end
$var wire 3 - index [2:0] $end
$var wire 1 % data_out $end
$var wire 8 . data_in [7:0] $end
$var wire 1 ) clk_32f $end
$var wire 1 / _41_ $end
$var wire 1 0 _40_ $end
$var wire 1 1 _39_ $end
$var wire 1 2 _38_ $end
$var wire 1 3 _37_ $end
$var wire 1 4 _36_ $end
$var wire 1 5 _35_ $end
$var wire 1 6 _34_ $end
$var wire 1 7 _33_ $end
$var wire 1 8 _32_ $end
$var wire 1 9 _31_ $end
$var wire 1 : _30_ $end
$var wire 1 ; _29_ $end
$var wire 1 < _28_ $end
$var wire 1 = _27_ $end
$var wire 1 > _26_ $end
$var wire 1 ? _25_ $end
$var wire 1 @ _24_ $end
$var wire 1 A _23_ $end
$var wire 1 B _22_ $end
$var wire 1 C _21_ $end
$var wire 1 D _20_ $end
$var wire 1 E _19_ $end
$var wire 1 F _18_ $end
$var wire 1 G _17_ $end
$var wire 1 H _16_ $end
$var wire 1 I _15_ $end
$var wire 1 J _14_ $end
$var wire 1 K _13_ $end
$var wire 1 L _12_ $end
$var wire 1 M _11_ $end
$var wire 1 N _10_ $end
$var wire 1 O _09_ $end
$var wire 1 P _08_ $end
$var wire 1 Q _07_ $end
$var wire 1 R _06_ $end
$var wire 1 S _05_ $end
$var wire 1 T _04_ $end
$var wire 1 U _03_ $end
$var wire 1 V _02_ $end
$var wire 1 W _01_ $end
$var wire 3 X _00_ [2:0] $end
$scope module _42_ $end
$var wire 1 W Y $end
$var wire 1 # A $end
$upscope $end
$scope module _43_ $end
$var wire 1 Y A $end
$var wire 1 V Y $end
$upscope $end
$scope module _44_ $end
$var wire 1 U Y $end
$var wire 1 $ A $end
$upscope $end
$scope module _45_ $end
$var wire 1 Z A $end
$var wire 1 T Y $end
$upscope $end
$scope module _46_ $end
$var wire 1 [ A $end
$var wire 1 S Y $end
$upscope $end
$scope module _47_ $end
$var wire 1 U A $end
$var wire 1 \ B $end
$var wire 1 ] Y $end
$upscope $end
$scope module _48_ $end
$var wire 1 ^ A $end
$var wire 1 _ B $end
$var wire 1 R Y $end
$upscope $end
$scope module _49_ $end
$var wire 1 R A $end
$var wire 1 Q Y $end
$upscope $end
$scope module _50_ $end
$var wire 1 ` A $end
$var wire 1 a B $end
$var wire 1 P Y $end
$upscope $end
$scope module _51_ $end
$var wire 1 P A $end
$var wire 1 O Y $end
$upscope $end
$scope module _52_ $end
$var wire 1 O B $end
$var wire 1 N Y $end
$var wire 1 $ A $end
$upscope $end
$scope module _53_ $end
$var wire 1 Q A $end
$var wire 1 N B $end
$var wire 1 b Y $end
$upscope $end
$scope module _54_ $end
$var wire 1 S A $end
$var wire 1 R B $end
$var wire 1 M Y $end
$upscope $end
$scope module _55_ $end
$var wire 1 S A $end
$var wire 1 R B $end
$var wire 1 L Y $end
$upscope $end
$scope module _56_ $end
$var wire 1 L B $end
$var wire 1 K Y $end
$var wire 1 $ A $end
$upscope $end
$scope module _57_ $end
$var wire 1 M A $end
$var wire 1 K B $end
$var wire 1 c Y $end
$upscope $end
$scope module _58_ $end
$var wire 1 W A $end
$var wire 1 d B $end
$var wire 1 J Y $end
$upscope $end
$scope module _59_ $end
$var wire 1 e A $end
$var wire 1 R B $end
$var wire 1 I Y $end
$upscope $end
$scope module _60_ $end
$var wire 1 J A $end
$var wire 1 I B $end
$var wire 1 H Y $end
$upscope $end
$scope module _61_ $end
$var wire 1 H B $end
$var wire 1 G Y $end
$var wire 1 $ A $end
$upscope $end
$scope module _62_ $end
$var wire 1 G A $end
$var wire 1 F Y $end
$upscope $end
$scope module _63_ $end
$var wire 1 P B $end
$var wire 1 E Y $end
$var wire 1 # A $end
$upscope $end
$scope module _64_ $end
$var wire 1 f A $end
$var wire 1 S B $end
$var wire 1 D Y $end
$upscope $end
$scope module _65_ $end
$var wire 1 g A $end
$var wire 1 h B $end
$var wire 1 C Y $end
$upscope $end
$scope module _66_ $end
$var wire 1 D A $end
$var wire 1 C B $end
$var wire 1 B Y $end
$upscope $end
$scope module _67_ $end
$var wire 1 E A $end
$var wire 1 B B $end
$var wire 1 A Y $end
$upscope $end
$scope module _68_ $end
$var wire 1 i A $end
$var wire 1 @ Y $end
$var wire 1 # B $end
$upscope $end
$scope module _69_ $end
$var wire 1 M A $end
$var wire 1 @ B $end
$var wire 1 ? Y $end
$upscope $end
$scope module _70_ $end
$var wire 1 ? A $end
$var wire 1 > Y $end
$upscope $end
$scope module _71_ $end
$var wire 1 A A $end
$var wire 1 > B $end
$var wire 1 = Y $end
$upscope $end
$scope module _72_ $end
$var wire 1 F A $end
$var wire 1 = B $end
$var wire 1 < Y $end
$upscope $end
$scope module _73_ $end
$var wire 1 j A $end
$var wire 1 J B $end
$var wire 1 ; Y $end
$upscope $end
$scope module _74_ $end
$var wire 1 k A $end
$var wire 1 T B $end
$var wire 1 : Y $end
$upscope $end
$scope module _75_ $end
$var wire 1 W A $end
$var wire 1 l B $end
$var wire 1 9 Y $end
$upscope $end
$scope module _76_ $end
$var wire 1 S A $end
$var wire 1 9 B $end
$var wire 1 8 Y $end
$upscope $end
$scope module _77_ $end
$var wire 1 : A $end
$var wire 1 8 B $end
$var wire 1 7 Y $end
$upscope $end
$scope module _78_ $end
$var wire 1 ; A $end
$var wire 1 7 B $end
$var wire 1 6 Y $end
$upscope $end
$scope module _79_ $end
$var wire 1 V A $end
$var wire 1 J B $end
$var wire 1 5 Y $end
$upscope $end
$scope module _80_ $end
$var wire 1 m B $end
$var wire 1 4 Y $end
$var wire 1 # A $end
$upscope $end
$scope module _81_ $end
$var wire 1 n A $end
$var wire 1 4 B $end
$var wire 1 3 Y $end
$upscope $end
$scope module _82_ $end
$var wire 1 5 A $end
$var wire 1 3 B $end
$var wire 1 2 Y $end
$upscope $end
$scope module _83_ $end
$var wire 1 o A $end
$var wire 1 T B $end
$var wire 1 1 Y $end
$upscope $end
$scope module _84_ $end
$var wire 1 2 A $end
$var wire 1 1 B $end
$var wire 1 0 Y $end
$upscope $end
$scope module _85_ $end
$var wire 1 6 A $end
$var wire 1 0 B $end
$var wire 1 / Y $end
$upscope $end
$scope module _86_ $end
$var wire 1 < A $end
$var wire 1 / B $end
$var wire 1 % Y $end
$upscope $end
$scope module _87_ $end
$var wire 1 p D $end
$var wire 1 ) C $end
$var reg 1 q Q $end
$upscope $end
$scope module _88_ $end
$var wire 1 r D $end
$var wire 1 ) C $end
$var reg 1 s Q $end
$upscope $end
$scope module _89_ $end
$var wire 1 t D $end
$var wire 1 ) C $end
$var reg 1 u Q $end
$upscope $end
$upscope $end
$scope module probador $end
$var wire 1 & data_out_cond $end
$var wire 1 % data_out_synth $end
$var reg 1 ) clk_32f $end
$var reg 1 ( clk_4f $end
$var reg 8 v data_in [7:0] $end
$var reg 1 $ reset_L $end
$var reg 1 # valid_in $end
$var integer 32 w check [31:0] $end
$upscope $end
$upscope $end
$scope module DFFSR $end
$var wire 1 x C $end
$var wire 1 y D $end
$var wire 1 z R $end
$var wire 1 { S $end
$var reg 1 | Q $end
$upscope $end
$enddefinitions $end
#0
$dumpvars
x|
z{
zz
zy
zx
b1 w
b11001100 v
0u
0t
0s
0r
0q
0p
0o
0n
0m
1l
0k
1j
0i
0h
1g
1f
0e
0d
0c
0b
0a
0`
0_
0^
0]
0\
0[
0Z
0Y
b0 X
0W
1V
1U
1T
1S
1R
0Q
1P
0O
1N
0M
0L
1K
1J
0I
1H
1G
0F
0E
0D
1C
1B
0A
1@
1?
0>
1=
1<
0;
1:
09
08
07
16
05
14
13
12
01
10
0/
b11001100 .
b0 -
b0 ,
b11001100 +
b11001100 *
1)
1(
b11001100 '
0&
0%
0$
1#
z"
z!
$end
#10
0)
#20
1)
#30
0)
#40
1)
#50
0)
#60
1)
#70
0)
#80
1)
0(
#90
0)
#100
1)
#110
0)
#120
1)
#130
0)
#140
1)
#150
0)
#160
b1 w
1%
02
0<
1p
15
1F
b1 X
1]
04
19
1;
0G
0V
0U
1m
0l
0j
1Y
1&
b10101010 +
1$
b10101010 '
b10101010 *
b10101010 .
b10101010 v
1)
1(
#170
0)
#180
b1 w
0%
1/
1r
1b
06
0N
17
1E
1O
0p
0:
0P
b10 X
0]
1o
1k
1`
1^
1\
0&
b1 -
1q
b1 ,
1)
#190
0)
#200
b1 w
1%
0/
16
07
1p
11
1:
b11 X
1]
0T
1&
0o
0k
0`
0^
0\
1a
1_
1Z
b10 ,
0q
b10 -
1s
1)
#210
0)
#220
b1 w
0%
1<
1t
0F
1c
1G
0r
0K
0H
0b
1L
1I
1Q
0p
01
0R
b100 X
0]
1o
1k
1`
1^
1\
0&
b11 -
1q
b11 ,
1)
#230
0)
#240
b1 w
1%
0<
1=
1F
0r
0G
1t
0>
1N
0b
1c
1?
0E
0I
1H
1p
0O
0Q
0M
1D
b101 X
1]
1P
1R
0C
0J
1T
0S
1&
0o
0k
0`
0^
0\
0a
0_
0Z
1n
1h
1d
1[
b100 ,
0q
0s
b100 -
1u
1)
0(
#250
0)
#260
b1 w
0%
1/
1r
1b
06
0N
17
1E
1O
0p
0:
0P
b110 X
0]
1o
1k
1`
1^
1\
0&
b101 -
1q
b101 ,
1)
#270
0)
#280
b1 w
1%
0/
16
07
1p
11
1:
b111 X
1]
0T
1&
0o
0k
0`
0^
0\
1a
1_
1Z
b110 ,
0q
b110 -
1s
1)
#290
0)
#300
b1 w
0%
1<
0=
0t
1>
0r
0c
0?
0b
1M
1I
1Q
0p
01
0R
b0 X
0]
1o
1k
1`
1^
1\
0&
b111 -
1q
b111 ,
1)
#310
0)
#320
b1 w
1%
0<
1=
0r
1K
0t
0>
1N
0b
0c
1?
0L
1p
0O
0Q
0M
0D
b1 X
1]
1P
1R
1C
0I
09
1T
1S
1V
14
0o
0k
0`
0^
0\
0a
0_
0Z
0n
0h
0d
0[
0m
1l
1j
1i
1e
0Y
1W
1&
b10111100 +
b0 ,
0q
0s
b0 -
0u
b11011101 '
b11011101 *
b11011101 .
b11011101 v
0#
1)
1(
#330
0)
#340
b1 w
0%
1/
1r
1b
06
0N
17
1O
0p
0:
0P
b10 X
0]
1o
1k
1`
1^
1\
0&
b1 -
1q
b1 ,
1)
#350
0)
#360
b1 w
1%
0/
16
07
1p
11
1:
b11 X
1]
0T
1&
0o
0k
0`
0^
0\
1a
1_
1Z
b10 ,
0q
b10 -
1s
1)
#370
0)
#380
1t
1c
0r
0K
0b
1L
1Q
0p
01
0R
b100 X
0]
1o
1k
1`
1^
1\
b11 -
1q
b11 ,
1)
#390
0)
#400
b1 w
1%
0<
1=
0r
1t
0>
1N
0b
1c
1?
12
1p
0O
0Q
0M
1D
18
b101 X
1]
1P
1R
03
0C
1T
0S
0o
0k
0`
0^
0\
0a
0_
0Z
1n
1h
1d
1[
b100 ,
0q
0s
b100 -
1u
1)
0(
#410
0)
#420
1r
1b
0N
1O
0p
0:
0P
b110 X
0]
1o
1k
1`
1^
1\
b101 -
1q
b101 ,
1)
#430
0)
#440
b1 w
0%
1/
00
1p
11
1:
b111 X
1]
0T
0&
0o
0k
0`
0^
0\
1a
1_
1Z
b110 ,
0q
b110 -
1s
1)
#450
0)
#460
b1 w
1<
0=
0%
0t
1>
0/
0r
0c
0?
0b
10
1M
1Q
0p
01
0R
b0 X
0]
1o
1k
1`
1^
1\
b111 -
1q
b111 ,
1)
#470
0)
#480
b1 w
1%
0<
0r
1K
0t
1=
1N
0b
0c
0E
0L
02
0>
0;
1p
0O
0Q
0M
0D
08
1?
b1 X
1]
1P
1R
13
1C
04
1J
1T
1S
0V
0@
0o
0k
0`
0^
0\
0a
0_
0Z
0n
0h
0d
0[
1m
1Y
0W
1&
b11111111 +
b0 ,
0q
0s
b0 -
0u
b11111111 '
b11111111 *
b11111111 .
b11111111 v
1#
1)
1(
#490
0)
#500
1r
1b
0N
17
1E
1O
0p
0:
0P
b10 X
0]
1o
1k
1`
1^
1\
b1 -
1q
b1 ,
1)
#510
0)
#520
07
1p
11
1:
b11 X
1]
0T
0o
0k
0`
0^
0\
1a
1_
1Z
b10 ,
0q
b10 -
1s
1)
#530
0)
#540
1t
1c
0r
0K
0b
1L
1Q
0p
01
0R
b100 X
0]
1o
1k
1`
1^
1\
b11 -
1q
b11 ,
1)
#550
0)
#560
0r
1t
1N
0b
1c
0E
1;
1p
0O
0Q
0M
1D
18
b101 X
1]
1P
1R
0C
0J
1T
0S
0o
0k
0`
0^
0\
0a
0_
0Z
1n
1h
1d
1[
b100 ,
0q
0s
b100 -
1u
1)
0(
#570
0)
#580
1r
1b
0N
1E
1O
0p
0:
0P
b110 X
0]
1o
1k
1`
1^
1\
b101 -
1q
b101 ,
1)
#590
0)
#600
1p
11
1:
b111 X
1]
0T
0o
0k
0`
0^
0\
1a
1_
1Z
b110 ,
0q
b110 -
1s
1)
#610
0)
#620
0t
0r
0c
0b
1M
1Q
0p
01
0R
b0 X
0]
1o
1k
1`
1^
1\
b111 -
1q
b111 ,
1)
#630
0)
#640
b1 w
1%
0<
1=
1F
0r
1K
0t
0G
1N
0b
0c
0>
0E
0L
0;
1?
1H
1p
0O
0Q
0M
0D
08
b1 X
1]
1P
1R
1C
1J
1@
0I
1T
1S
0o
0k
0`
0^
0\
0a
0_
0Z
0n
0h
0d
0[
0i
0e
b11101110 +
b0 ,
0q
0s
b0 -
0u
b11101110 '
b11101110 *
b11101110 .
b11101110 v
1)
1(
#650
0)
#660
1r
1b
0N
17
1E
1O
0p
0:
0P
b10 X
0]
1o
1k
1`
1^
1\
b1 -
1q
b1 ,
1)
#670
0)
#680
07
1p
11
1:
b11 X
1]
0T
0o
0k
0`
0^
0\
1a
1_
1Z
b10 ,
0q
b10 -
1s
1)
#690
0)
#700
b1 w
0%
1<
1t
0F
1c
1G
0r
0K
0H
0b
1L
1I
1Q
0p
01
0R
b100 X
0]
1o
1k
1`
1^
1\
0&
b11 -
1q
b11 ,
1)
#710
0)
#720
b1 w
1%
0<
1=
1F
0r
0G
1t
0>
1N
0b
1c
1?
0E
0I
1H
1;
1p
0O
0Q
0M
1D
18
b101 X
1]
1P
1R
0C
0J
1T
0S
1&
0o
0k
0`
0^
0\
0a
0_
0Z
1n
1h
1d
1[
b100 ,
0q
0s
b100 -
1u
1)
0(
#730
0)
#740
1r
1b
0N
1E
1O
0p
0:
0P
b110 X
0]
1o
1k
1`
1^
1\
b101 -
1q
b101 ,
1)
#750
0)
#760
1p
11
1:
b111 X
1]
0T
0o
0k
0`
0^
0\
1a
1_
1Z
b110 ,
0q
b110 -
1s
1)
#770
0)
#780
b1 w
0%
1<
0=
0t
1>
0r
0c
0?
0b
1M
1I
1Q
0p
01
0R
b0 X
0]
1o
1k
1`
1^
1\
0&
b111 -
1q
b111 ,
1)
#790
0)
#800
b1 w
1%
0<
1=
1F
0r
1K
0G
0t
0>
1N
0b
0c
1?
0E
0L
0I
1H
0;
1p
0O
0Q
0M
0D
08
b1 X
1]
1P
1R
1C
1J
1T
1S
1&
0o
0k
0`
0^
0\
0a
0_
0Z
0n
0h
0d
0[
b0 ,
0q
0s
b0 -
0u
1)
1(
