phy_rx/serial_paralelo_rx/probador.v
/* Genera señales para probar el phyrx.*/
module probador(
    output reg clk_4f,
    output reg clk_32f,
	output reg data_in
    ); 


    // Relojes
    initial	clk_4f 	<= 1;
    initial	clk_32f <= 1;

    always	#20 clk_4f 	<= ~clk_4f; 
    always	#160 clk_32f 	<= ~clk_32f; 


	reg [7:0]data;
	initial begin
		$dumpfile("senales_serial_paralelo.vcd");	// Nombre de archivo del "dump"
		$dumpvars;			        // Directiva para "dumpear" variables
		
		data_in <= 0;
        
		data <= 0;
		
		@(posedge clk_4f);
		repeat (4) begin
			repeat (4) begin
				data_in <= 1;
                
				@(posedge clk_32f);
				data_in <= 0;
                
				@(posedge clk_32f);
				data_in <= 1;
                
				@(posedge clk_32f);
				data_in <= 1;
                
				@(posedge clk_32f);
				data_in <= 1;
                
				@(posedge clk_32f);
				data_in <= 1;
                
				@(posedge clk_32f);
				data_in <= 0;
                
				@(posedge clk_32f);
				data_in <= 0;
                
				@(posedge clk_32f);
				data  <= 'hBC;
				
			end

				data_in <= 1;
                
				@(posedge clk_32f);
				data_in <= 1;
                
				@(posedge clk_32f);
				data_in <= 1;
                
				@(posedge clk_32f);
				data_in <= 1;
                
				@(posedge clk_32f);
				data_in <= 0;
                
				@(posedge clk_32f);
				data_in <= 0;
                
				@(posedge clk_32f);
				data_in <= 1;
                
				@(posedge clk_32f);
				data_in <= 0;
                
				@(posedge clk_32f);
				data  <= 'hF2;
				

				data_in <= 0;
                
				@(posedge clk_32f);
				data_in <= 0;
                
				@(posedge clk_32f);
				data_in <= 0;
                
				@(posedge clk_32f);
				data_in <= 1;
                
				@(posedge clk_32f);
				data_in <= 0;
                
				@(posedge clk_32f);
				data_in <= 1;
                
				@(posedge clk_32f);
				data_in <= 0;
                
				@(posedge clk_32f);
				data_in <= 1;
                
				@(posedge clk_32f);
				data  <= 'h15;
				

				data_in <= 1;
                
				@(posedge clk_32f);
				data_in <= 1;
                
				@(posedge clk_32f);
				data_in <= 0;
                
				@(posedge clk_32f);
				data_in <= 1;
                
				@(posedge clk_32f);
				data_in <= 1;
                
				@(posedge clk_32f);
				data_in <= 1;
                
				@(posedge clk_32f);
				data_in <= 0;
                
				@(posedge clk_32f);
				data_in <= 1;
                
				@(posedge clk_32f);
				data  <= 'hDD;
				

				data_in <= 0;
                
				@(posedge clk_32f);
				data_in <= 1;
                
				@(posedge clk_32f);
				data_in <= 0;
                
				@(posedge clk_32f);
				data_in <= 0;
                
				@(posedge clk_32f);
				data_in <= 0;
                
				@(posedge clk_32f);
				data_in <= 1;
                
				@(posedge clk_32f);
				data_in <= 0;
                
				@(posedge clk_32f);
				data_in <= 1;
                
				@(posedge clk_32f);
				data  <= 'h45;
				

			repeat (4) begin
				data_in <= 1;
                
				@(posedge clk_32f);
				data_in <= 0;
                
				@(posedge clk_32f);
				data_in <= 1;
                
				@(posedge clk_32f);
				data_in <= 1;
                
				@(posedge clk_32f);
				data_in <= 1;
                
				@(posedge clk_32f);
				data_in <= 1;
                
				@(posedge clk_32f);
				data_in <= 0;
                
				@(posedge clk_32f);
				data_in <= 0;
                
				@(posedge clk_32f);
				data  <= 'hBC;
				
			end


				data_in <= 1;
                
				@(posedge clk_32f);
				data_in <= 0;
                
				@(posedge clk_32f);
				data_in <= 1;
                
				@(posedge clk_32f);
				data_in <= 0;
                
				@(posedge clk_32f);
				data_in <= 1;
                
				@(posedge clk_32f);
				data_in <= 0;
                
				@(posedge clk_32f);
				data_in <= 1;
                
				@(posedge clk_32f);
				data_in <= 0;
                
				@(posedge clk_32f);
				data  <= 'hAA;
			

				data_in <= 1;
                
				@(posedge clk_32f);
				data_in <= 1;
                
				@(posedge clk_32f);
				data_in <= 1;
                
				@(posedge clk_32f);
				data_in <= 0;
                
				@(posedge clk_32f);
				data_in <= 1;
                
				@(posedge clk_32f);
				data_in <= 1;
                
				@(posedge clk_32f);
				data_in <= 1;
                
				@(posedge clk_32f);
				data_in <= 0;
                
				@(posedge clk_32f);
				data  <= 'hEE;
				

				data_in <= 0;
                
				@(posedge clk_32f);
				data_in <= 0;
                
				@(posedge clk_32f);
				data_in <= 0;
                
				@(posedge clk_32f);
				data_in <= 1;
            
				@(posedge clk_32f);
				data_in <= 0;
                
				@(posedge clk_32f);
				data_in <= 0;
                
				@(posedge clk_32f);
				data_in <= 1;
                
				@(posedge clk_32f);
				data_in <= 1;
                
				@(posedge clk_32f);
				data  <= 'h13;
				

				data_in <= 1;
                
				@(posedge clk_32f);
				data_in <= 1;
                
				@(posedge clk_32f);
				data_in <= 0;
                
				@(posedge clk_32f);
				data_in <= 0;
                
				@(posedge clk_32f);
				data_in <= 1;
                
				@(posedge clk_32f);
				data_in <= 1;
                
				@(posedge clk_32f);
				data_in <= 0;
                
				@(posedge clk_32f);
				data_in <= 1;
                
				@(posedge clk_32f);
				data  <= 'hCD;
				

			repeat (4) begin
				data_in <= 1;
                
				@(posedge clk_32f);
				data_in <= 0;
                
				@(posedge clk_32f);
				data_in <= 1;
                
				@(posedge clk_32f);
				data_in <= 1;
                
				@(posedge clk_32f);
				data_in <= 1;
                
				@(posedge clk_32f);
				data_in <= 1;
                
				@(posedge clk_32f);
				data_in <= 0;
                
				@(posedge clk_32f);
				data_in <= 0;
                
				@(posedge clk_32f);
				data  <= 'hBC;
				
			end

			
		end 

		$finish;
	end


endmodule

phy_rx/serial_paralelo_rx/module_serial_paralelo.v
module module_serial_paralelo (
    output reg [7:0]sp_out,
    output reg valid_out_sp,
    input data_in,
    input clk_4f,
    input clk_32f);
    

    reg [7:0] serial_in,q1;
    reg [2:0] counter;
    reg [2:0] BCcounter;

    
    always @(posedge clk_32f) begin

            
        
            if (counter == 0) begin
                serial_in[7] <= data_in;
                counter <= counter + 1;
                q1 <= serial_in;
            end
            if (counter == 1) begin
                serial_in[6] <= data_in;
                counter <= counter + 1; 
            end
            if (counter == 2) begin
                serial_in[5] <= data_in;
                counter <= counter + 1; 
            end
            if (counter == 3) begin
                serial_in[4] <= data_in;
                counter <= counter + 1; 
            end
            if (counter == 4) begin
                serial_in[3] <= data_in;
                counter <= counter + 1; 
            end
            if (counter == 5) begin
                serial_in[2] <= data_in;
                counter <= counter + 1; 
            end
            if (counter == 6) begin
                serial_in[1] <= data_in;
                counter <= counter + 1;                    
            end
            if (counter == 7) begin
                serial_in[0] <= data_in;
                counter <= counter + 1;
            end
        
    end

    always @(posedge clk_4f) begin
        
            sp_out <= q1;
            if (q1 == 'hBC) begin
                BCcounter <= BCcounter + 1;
                
                
                valid_out_sp <= 0;
                end
        else begin
            if (BCcounter == 4) begin
                
                
                valid_out_sp <= 1;
                
            end
        end 
        if (BCcounter == 4) begin
            if (q1 == 'hBC) begin
                BCcounter <= 'b100;
            end
            end
        end

    

endmodule

phy_rx/serial_paralelo_rx/Banco_Pruebas.v
/* Banco de pruebas para el módulo: phyrx. Prueba la descripción conductual y la estructural a partir del probador: probadorRx2.v*/
`timescale 	1ns				/ 100ps

`include "module_serial_paralelo.v"
`include "probador.v"

module BancoPruebas;
    /*AUTOWIRE*/
    // Beginning of automatic wires (for undeclared instantiated-module outputs)
    wire		clk_32f;		// From probador_ of probador.v
    wire		clk_4f;			// From probador_ of probador.v
    wire		data_in;		// From probador_ of probador.v
    wire [7:0]		sp_out;			// From module_serial_paralelo_ of module_serial_paralelo.v
    wire		valid_out_sp;		// From module_serial_paralelo_ of module_serial_paralelo.v
    // End of automatics


    module_serial_paralelo module_serial_paralelo_(/*AUTOINST*/
						   // Outputs
						   .sp_out		(sp_out[7:0]),
						   .valid_out_sp	(valid_out_sp),
						   // Inputs
						   .data_in		(data_in),
						   .clk_4f		(clk_4f),
						   .clk_32f		(clk_32f));
		         


	probador probador_(/*AUTOINST*/
			   // Outputs
			   .clk_4f		(clk_4f),
			   .clk_32f		(clk_32f),
			   .data_in		(data_in));
			       


endmodule

phy_rx/serial_paralelo_rx/senales_serial_paralelo.vcd
$date
	Tue Jun  1 18:15:43 2021
$end
$version
	Icarus Verilog
$end
$timescale
	100ps
$end
$scope module BancoPruebas $end
$var wire 1 ! valid_out_sp $end
$var wire 8 " sp_out [7:0] $end
$var wire 1 # data_in $end
$var wire 1 $ clk_4f $end
$var wire 1 % clk_32f $end
$scope module module_serial_paralelo_ $end
$var wire 1 # data_in $end
$var wire 1 $ clk_4f $end
$var wire 1 % clk_32f $end
$var reg 3 & BCcounter [2:0] $end
$var reg 3 ' counter [2:0] $end
$var reg 8 ( q1 [7:0] $end
$var reg 8 ) serial_in [7:0] $end
$var reg 8 * sp_out [7:0] $end
$var reg 1 ! valid_out_sp $end
$upscope $end
$scope module probador_ $end
$var reg 1 % clk_32f $end
$var reg 1 $ clk_4f $end
$var reg 8 + data [7:0] $end
$var reg 1 # data_in $end
$upscope $end
$upscope $end
$enddefinitions $end
#0
$dumpvars
b0 +
bx *
bx )
bx (
bx '
bx &
1%
1$
1#
bx "
x!
$end
#500
0%
#1000
0#
1%
#1500
0%
#2000
1#
1%
#2500
0%
0$
#3000
1%
#3500
0%
#4000
1%
#4500
0%
#5000
1%
1$
#5500
0%
#6000
0#
1%
#6500
0%
#7000
1%
#7500
0%
0$
#8000
1#
b10111100 +
1%
#8500
0%
#9000
0#
1%
#9500
0%
#10000
1#
1%
1$
#10500
0%
#11000
1%
#11500
0%
#12000
1%
#12500
0%
0$
#13000
1%
#13500
0%
#14000
0#
1%
#14500
0%
#15000
1%
1$
#15500
0%
#16000
1#
1%
#16500
0%
#17000
0#
1%
#17500
0%
0$
#18000
1#
1%
#18500
0%
#19000
1%
#19500
0%
#20000
1%
1$
#20500
0%
#21000
1%
#21500
0%
#22000
0#
1%
#22500
0%
0$
#23000
1%
#23500
0%
#24000
1#
1%
#24500
0%
#25000
0#
1%
1$
#25500
0%
#26000
1#
1%
#26500
0%
#27000
1%
#27500
0%
0$
#28000
1%
#28500
0%
#29000
1%
#29500
0%
#30000
0#
1%
1$
#30500
0%
#31000
1%
#31500
0%
#32000
1#
1%
#32500
0%
0$
#33000
1%
#33500
0%
#34000
1%
#34500
0%
#35000
1%
1$
#35500
0%
#36000
0#
1%
#36500
0%
#37000
1%
#37500
0%
0$
#38000
1#
1%
#38500
0%
#39000
0#
1%
#39500
0%
#40000
b11110010 +
1%
1$
#40500
0%
#41000
1%
#41500
0%
#42000
1%
#42500
0%
0$
#43000
1#
1%
#43500
0%
#44000
0#
1%
#44500
0%
#45000
1#
1%
1$
#45500
0%
#46000
0#
1%
#46500
0%
#47000
1#
1%
#47500
0%
0$
#48000
b10101 +
1%
#48500
0%
#49000
1%
#49500
0%
#50000
0#
1%
1$
#50500
0%
#51000
1#
1%
#51500
0%
#52000
1%
#52500
0%
0$
#53000
1%
#53500
0%
#54000
0#
1%
#54500
0%
#55000
1#
1%
1$
#55500
0%
#56000
0#
b11011101 +
1%
#56500
0%
#57000
1#
1%
#57500
0%
0$
#58000
0#
1%
#58500
0%
#59000
1%
#59500
0%
#60000
1%
1$
#60500
0%
#61000
1#
1%
#61500
0%
#62000
0#
1%
#62500
0%
0$
#63000
1#
1%
#63500
0%
#64000
b1000101 +
1%
#64500
0%
#65000
0#
1%
1$
#65500
0%
#66000
1#
1%
#66500
0%
#67000
1%
#67500
0%
0$
#68000
1%
#68500
0%
#69000
1%
#69500
0%
#70000
0#
1%
1$
#70500
0%
#71000
1%
#71500
0%
#72000
1#
b10111100 +
1%
#72500
0%
0$
#73000
0#
1%
#73500
0%
#74000
1#
1%
#74500
0%
#75000
1%
1$
#75500
0%
#76000
1%
#76500
0%
#77000
1%
#77500
0%
0$
#78000
0#
1%
#78500
0%
#79000
1%
#79500
0%
#80000
1#
1%
1$
#80500
0%
#81000
0#
1%
#81500
0%
#82000
1#
1%
#82500
0%
0$
#83000
1%
#83500
0%
#84000
1%
#84500
0%
#85000
1%
1$
#85500
0%
#86000
0#
1%
#86500
0%
#87000
1%
#87500
0%
0$
#88000
1#
1%
#88500
0%
#89000
0#
1%
#89500
0%
#90000
1#
1%
1$
#90500
0%
#91000
1%
#91500
0%
#92000
1%
#92500
0%
0$
#93000
1%
#93500
0%
#94000
0#
1%
#94500
0%
#95000
1%
1$
#95500
0%
#96000
1#
1%
#96500
0%
#97000
0#
1%
#97500
0%
0$
#98000
1#
1%
#98500
0%
#99000
0#
1%
#99500
0%
#100000
1#
1%
1$
#100500
0%
#101000
0#
1%
#101500
0%
#102000
1#
1%
#102500
0%
0$
#103000
0#
1%
#103500
0%
#104000
1#
b10101010 +
1%
#104500
0%
#105000
1%
1$
#105500
0%
#106000
1%
#106500
0%
#107000
0#
1%
#107500
0%
0$
#108000
1#
1%
#108500
0%
#109000
1%
#109500
0%
#110000
1%
1$
#110500
0%
#111000
0#
1%
#111500
0%
#112000
b11101110 +
1%
#112500
0%
0$
#113000
1%
#113500
0%
#114000
1%
#114500
0%
#115000
1#
1%
1$
#115500
0%
#116000
0#
1%
#116500
0%
#117000
1%
#117500
0%
0$
#118000
1#
1%
#118500
0%
#119000
1%
#119500
0%
#120000
b10011 +
1%
1$
#120500
0%
#121000
1%
#121500
0%
#122000
0#
1%
#122500
0%
0$
#123000
1%
#123500
0%
#124000
1#
1%
#124500
0%
#125000
1%
1$
#125500
0%
#126000
0#
1%
#126500
0%
#127000
1#
1%
#127500
0%
0$
#128000
b11001101 +
1%
#128500
0%
#129000
0#
1%
#129500
0%
#130000
1#
1%
1$
#130500
0%
#131000
1%
#131500
0%
#132000
1%
#132500
0%
0$
#133000
1%
#133500
0%
#134000
0#
1%
#134500
0%
#135000
1%
1$
#135500
0%
#136000
1#
b10111100 +
1%
#136500
0%
#137000
0#
1%
#137500
0%
0$
#138000
1#
1%
#138500
0%
#139000
1%
#139500
0%
#140000
1%
1$
#140500
0%
#141000
1%
#141500
0%
#142000
0#
1%
#142500
0%
0$
#143000
1%
#143500
0%
#144000
1#
1%
#144500
0%
#145000
0#
1%
1$
#145500
0%
#146000
1#
1%
#146500
0%
#147000
1%
#147500
0%
0$
#148000
1%
#148500
0%
#149000
1%
#149500
0%
#150000
0#
1%
1$
#150500
0%
#151000
1%
#151500
0%
#152000
1#
1%
#152500
0%
0$
#153000
0#
1%
#153500
0%
#154000
1#
1%
#154500
0%
#155000
1%
1$
#155500
0%
#156000
1%
#156500
0%
#157000
1%
#157500
0%
0$
#158000
0#
1%
#158500
0%
#159000
1%
#159500
0%
#160000
1#
1%
1$
#160500
0%
#161000
0#
1%
#161500
0%
#162000
1#
1%
#162500
0%
0$
#163000
1%
#163500
0%
#164000
1%
#164500
0%
#165000
1%
1$
#165500
0%
#166000
0#
1%
#166500
0%
#167000
1%
#167500
0%
0$
#168000
1#
1%
#168500
0%
#169000
0#
1%
#169500
0%
#170000
1#
1%
1$
#170500
0%
#171000
1%
#171500
0%
#172000
1%
#172500
0%
0$
#173000
1%
#173500
0%
#174000
0#
1%
#174500
0%
#175000
1%
1$
#175500
0%
#176000
1#
1%
#176500
0%
#177000
0#
1%
#177500
0%
0$
#178000
1#
1%
#178500
0%
#179000
1%
#179500
0%
#180000
1%
1$
#180500
0%
#181000
1%
#181500
0%
#182000
0#
1%
#182500
0%
0$
#183000
1%
#183500
0%
#184000
1#
1%
#184500
0%
#185000
0#
1%
1$
#185500
0%
#186000
1#
1%
#186500
0%
#187000
1%
#187500
0%
0$
#188000
1%
#188500
0%
#189000
1%
#189500
0%
#190000
0#
1%
1$
#190500
0%
#191000
1%
#191500
0%
#192000
1#
1%
#192500
0%
0$
#193000
1%
#193500
0%
#194000
1%
#194500
0%
#195000
1%
1$
#195500
0%
#196000
0#
1%
#196500
0%
#197000
1%
#197500
0%
0$
#198000
1#
1%
#198500
0%
#199000
0#
1%
#199500
0%
#200000
b11110010 +
1%
1$
#200500
0%
#201000
1%
#201500
0%
#202000
1%
#202500
0%
0$
#203000
1#
1%
#203500
0%
#204000
0#
1%
#204500
0%
#205000
1#
1%
1$
#205500
0%
#206000
0#
1%
#206500
0%
#207000
1#
1%
#207500
0%
0$
#208000
b10101 +
1%
#208500
0%
#209000
1%
#209500
0%
#210000
0#
1%
1$
#210500
0%
#211000
1#
1%
#211500
0%
#212000
1%
#212500
0%
0$
#213000
1%
#213500
0%
#214000
0#
1%
#214500
0%
#215000
1#
1%
1$
#215500
0%
#216000
0#
b11011101 +
1%
#216500
0%
#217000
1#
1%
#217500
0%
0$
#218000
0#
1%
#218500
0%
#219000
1%
#219500
0%
#220000
1%
1$
#220500
0%
#221000
1#
1%
#221500
0%
#222000
0#
1%
#222500
0%
0$
#223000
1#
1%
#223500
0%
#224000
b1000101 +
1%
#224500
0%
#225000
0#
1%
1$
#225500
0%
#226000
1#
1%
#226500
0%
#227000
1%
#227500
0%
0$
#228000
1%
#228500
0%
#229000
1%
#229500
0%
#230000
0#
1%
1$
#230500
0%
#231000
1%
#231500
0%
#232000
1#
b10111100 +
1%
#232500
0%
0$
#233000
0#
1%
#233500
0%
#234000
1#
1%
#234500
0%
#235000
1%
1$
#235500
0%
#236000
1%
#236500
0%
#237000
1%
#237500
0%
0$
#238000
0#
1%
#238500
0%
#239000
1%
#239500
0%
#240000
1#
1%
1$
#240500
0%
#241000
0#
1%
#241500
0%
#242000
1#
1%
#242500
0%
0$
#243000
1%
#243500
0%
#244000
1%
#244500
0%
#245000
1%
1$
#245500
0%
#246000
0#
1%
#246500
0%
#247000
1%
#247500
0%
0$
#248000
1#
1%
#248500
0%
#249000
0#
1%
#249500
0%
#250000
1#
1%
1$
#250500
0%
#251000
1%
#251500
0%
#252000
1%
#252500
0%
0$
#253000
1%
#253500
0%
#254000
0#
1%
#254500
0%
#255000
1%
1$
#255500
0%
#256000
1#
1%
#256500
0%
#257000
0#
1%
#257500
0%
0$
#258000
1#
1%
#258500
0%
#259000
0#
1%
#259500
0%
#260000
1#
1%
1$
#260500
0%
#261000
0#
1%
#261500
0%
#262000
1#
1%
#262500
0%
0$
#263000
0#
1%
#263500
0%
#264000
1#
b10101010 +
1%
#264500
0%
#265000
1%
1$
#265500
0%
#266000
1%
#266500
0%
#267000
0#
1%
#267500
0%
0$
#268000
1#
1%
#268500
0%
#269000
1%
#269500
0%
#270000
1%
1$
#270500
0%
#271000
0#
1%
#271500
0%
#272000
b11101110 +
1%
#272500
0%
0$
#273000
1%
#273500
0%
#274000
1%
#274500
0%
#275000
1#
1%
1$
#275500
0%
#276000
0#
1%
#276500
0%
#277000
1%
#277500
0%
0$
#278000
1#
1%
#278500
0%
#279000
1%
#279500
0%
#280000
b10011 +
1%
1$
#280500
0%
#281000
1%
#281500
0%
#282000
0#
1%
#282500
0%
0$
#283000
1%
#283500
0%
#284000
1#
1%
#284500
0%
#285000
1%
1$
#285500
0%
#286000
0#
1%
#286500
0%
#287000
1#
1%
#287500
0%
0$
#288000
b11001101 +
1%
#288500
0%
#289000
0#
1%
#289500
0%
#290000
1#
1%
1$
#290500
0%
#291000
1%
#291500
0%
#292000
1%
#292500
0%
0$
#293000
1%
#293500
0%
#294000
0#
1%
#294500
0%
#295000
1%
1$
#295500
0%
#296000
1#
b10111100 +
1%
#296500
0%
#297000
0#
1%
#297500
0%
0$
#298000
1#
1%
#298500
0%
#299000
1%
#299500
0%
#300000
1%
1$
#300500
0%
#301000
1%
#301500
0%
#302000
0#
1%
#302500
0%
0$
#303000
1%
#303500
0%
#304000
1#
1%
#304500
0%
#305000
0#
1%
1$
#305500
0%
#306000
1#
1%
#306500
0%
#307000
1%
#307500
0%
0$
#308000
1%
#308500
0%
#309000
1%
#309500
0%
#310000
0#
1%
1$
#310500
0%
#311000
1%
#311500
0%
#312000
1#
1%
#312500
0%
0$
#313000
0#
1%
#313500
0%
#314000
1#
1%
#314500
0%
#315000
1%
1$
#315500
0%
#316000
1%
#316500
0%
#317000
1%
#317500
0%
0$
#318000
0#
1%
#318500
0%
#319000
1%
#319500
0%
#320000
1#
1%
1$
#320500
0%
#321000
0#
1%
#321500
0%
#322000
1#
1%
#322500
0%
0$
#323000
1%
#323500
0%
#324000
1%
#324500
0%
#325000
1%
1$
#325500
0%
#326000
0#
1%
#326500
0%
#327000
1%
#327500
0%
0$
#328000
1#
1%
#328500
0%
#329000
0#
1%
#329500
0%
#330000
1#
1%
1$
#330500
0%
#331000
1%
#331500
0%
#332000
1%
#332500
0%
0$
#333000
1%
#333500
0%
#334000
0#
1%
#334500
0%
#335000
1%
1$
#335500
0%
#336000
1#
1%
#336500
0%
#337000
0#
1%
#337500
0%
0$
#338000
1#
1%
#338500
0%
#339000
1%
#339500
0%
#340000
1%
1$
#340500
0%
#341000
1%
#341500
0%
#342000
0#
1%
#342500
0%
0$
#343000
1%
#343500
0%
#344000
1#
1%
#344500
0%
#345000
0#
1%
1$
#345500
0%
#346000
1#
1%
#346500
0%
#347000
1%
#347500
0%
0$
#348000
1%
#348500
0%
#349000
1%
#349500
0%
#350000
0#
1%
1$
#350500
0%
#351000
1%
#351500
0%
#352000
1#
1%
#352500
0%
0$
#353000
1%
#353500
0%
#354000
1%
#354500
0%
#355000
1%
1$
#355500
0%
#356000
0#
1%
#356500
0%
#357000
1%
#357500
0%
0$
#358000
1#
1%
#358500
0%
#359000
0#
1%
#359500
0%
#360000
b11110010 +
1%
1$
#360500
0%
#361000
1%
#361500
0%
#362000
1%
#362500
0%
0$
#363000
1#
1%
#363500
0%
#364000
0#
1%
#364500
0%
#365000
1#
1%
1$
#365500
0%
#366000
0#
1%
#366500
0%
#367000
1#
1%
#367500
0%
0$
#368000
b10101 +
1%
#368500
0%
#369000
1%
#369500
0%
#370000
0#
1%
1$
#370500
0%
#371000
1#
1%
#371500
0%
#372000
1%
#372500
0%
0$
#373000
1%
#373500
0%
#374000
0#
1%
#374500
0%
#375000
1#
1%
1$
#375500
0%
#376000
0#
b11011101 +
1%
#376500
0%
#377000
1#
1%
#377500
0%
0$
#378000
0#
1%
#378500
0%
#379000
1%
#379500
0%
#380000
1%
1$
#380500
0%
#381000
1#
1%
#381500
0%
#382000
0#
1%
#382500
0%
0$
#383000
1#
1%
#383500
0%
#384000
b1000101 +
1%
#384500
0%
#385000
0#
1%
1$
#385500
0%
#386000
1#
1%
#386500
0%
#387000
1%
#387500
0%
0$
#388000
1%
#388500
0%
#389000
1%
#389500
0%
#390000
0#
1%
1$
#390500
0%
#391000
1%
#391500
0%
#392000
1#
b10111100 +
1%
#392500
0%
0$
#393000
0#
1%
#393500
0%
#394000
1#
1%
#394500
0%
#395000
1%
1$
#395500
0%
#396000
1%
#396500
0%
#397000
1%
#397500
0%
0$
#398000
0#
1%
#398500
0%
#399000
1%
#399500
0%
#400000
1#
1%
1$
#400500
0%
#401000
0#
1%
#401500
0%
#402000
1#
1%
#402500
0%
0$
#403000
1%
#403500
0%
#404000
1%
#404500
0%
#405000
1%
1$
#405500
0%
#406000
0#
1%
#406500
0%
#407000
1%
#407500
0%
0$
#408000
1#
1%
#408500
0%
#409000
0#
1%
#409500
0%
#410000
1#
1%
1$
#410500
0%
#411000
1%
#411500
0%
#412000
1%
#412500
0%
0$
#413000
1%
#413500
0%
#414000
0#
1%
#414500
0%
#415000
1%
1$
#415500
0%
#416000
1#
1%
#416500
0%
#417000
0#
1%
#417500
0%
0$
#418000
1#
1%
#418500
0%
#419000
0#
1%
#419500
0%
#420000
1#
1%
1$
#420500
0%
#421000
0#
1%
#421500
0%
#422000
1#
1%
#422500
0%
0$
#423000
0#
1%
#423500
0%
#424000
1#
b10101010 +
1%
#424500
0%
#425000
1%
1$
#425500
0%
#426000
1%
#426500
0%
#427000
0#
1%
#427500
0%
0$
#428000
1#
1%
#428500
0%
#429000
1%
#429500
0%
#430000
1%
1$
#430500
0%
#431000
0#
1%
#431500
0%
#432000
b11101110 +
1%
#432500
0%
0$
#433000
1%
#433500
0%
#434000
1%
#434500
0%
#435000
1#
1%
1$
#435500
0%
#436000
0#
1%
#436500
0%
#437000
1%
#437500
0%
0$
#438000
1#
1%
#438500
0%
#439000
1%
#439500
0%
#440000
b10011 +
1%
1$
#440500
0%
#441000
1%
#441500
0%
#442000
0#
1%
#442500
0%
0$
#443000
1%
#443500
0%
#444000
1#
1%
#444500
0%
#445000
1%
1$
#445500
0%
#446000
0#
1%
#446500
0%
#447000
1#
1%
#447500
0%
0$
#448000
b11001101 +
1%
#448500
0%
#449000
0#
1%
#449500
0%
#450000
1#
1%
1$
#450500
0%
#451000
1%
#451500
0%
#452000
1%
#452500
0%
0$
#453000
1%
#453500
0%
#454000
0#
1%
#454500
0%
#455000
1%
1$
#455500
0%
#456000
1#
b10111100 +
1%
#456500
0%
#457000
0#
1%
#457500
0%
0$
#458000
1#
1%
#458500
0%
#459000
1%
#459500
0%
#460000
1%
1$
#460500
0%
#461000
1%
#461500
0%
#462000
0#
1%
#462500
0%
0$
#463000
1%
#463500
0%
#464000
1#
1%
#464500
0%
#465000
0#
1%
1$
#465500
0%
#466000
1#
1%
#466500
0%
#467000
1%
#467500
0%
0$
#468000
1%
#468500
0%
#469000
1%
#469500
0%
#470000
0#
1%
1$
#470500
0%
#471000
1%
#471500
0%
#472000
1#
1%
#472500
0%
0$
#473000
0#
1%
#473500
0%
#474000
1#
1%
#474500
0%
#475000
1%
1$
#475500
0%
#476000
1%
#476500
0%
#477000
1%
#477500
0%
0$
#478000
0#
1%
#478500
0%
#479000
1%
#479500
0%
#480000
1#
1%
1$
#480500
0%
#481000
0#
1%
#481500
0%
#482000
1#
1%
#482500
0%
0$
#483000
1%
#483500
0%
#484000
1%
#484500
0%
#485000
1%
1$
#485500
0%
#486000
0#
1%
#486500
0%
#487000
1%
#487500
0%
0$
#488000
1#
1%
#488500
0%
#489000
0#
1%
#489500
0%
#490000
1#
1%
1$
#490500
0%
#491000
1%
#491500
0%
#492000
1%
#492500
0%
0$
#493000
1%
#493500
0%
#494000
0#
1%
#494500
0%
#495000
1%
1$
#495500
0%
#496000
1#
1%
#496500
0%
#497000
0#
1%
#497500
0%
0$
#498000
1#
1%
#498500
0%
#499000
1%
#499500
0%
#500000
1%
1$
#500500
0%
#501000
1%
#501500
0%
#502000
0#
1%
#502500
0%
0$
#503000
1%
#503500
0%
#504000
1#
1%
#504500
0%
#505000
0#
1%
1$
#505500
0%
#506000
1#
1%
#506500
0%
#507000
1%
#507500
0%
0$
#508000
1%
#508500
0%
#509000
1%
#509500
0%
#510000
0#
1%
1$
#510500
0%
#511000
1%
#511500
0%
#512000
1#
1%
#512500
0%
0$
#513000
1%
#513500
0%
#514000
1%
#514500
0%
#515000
1%
1$
#515500
0%
#516000
0#
1%
#516500
0%
#517000
1%
#517500
0%
0$
#518000
1#
1%
#518500
0%
#519000
0#
1%
#519500
0%
#520000
b11110010 +
1%
1$
#520500
0%
#521000
1%
#521500
0%
#522000
1%
#522500
0%
0$
#523000
1#
1%
#523500
0%
#524000
0#
1%
#524500
0%
#525000
1#
1%
1$
#525500
0%
#526000
0#
1%
#526500
0%
#527000
1#
1%
#527500
0%
0$
#528000
b10101 +
1%
#528500
0%
#529000
1%
#529500
0%
#530000
0#
1%
1$
#530500
0%
#531000
1#
1%
#531500
0%
#532000
1%
#532500
0%
0$
#533000
1%
#533500
0%
#534000
0#
1%
#534500
0%
#535000
1#
1%
1$
#535500
0%
#536000
0#
b11011101 +
1%
#536500
0%
#537000
1#
1%
#537500
0%
0$
#538000
0#
1%
#538500
0%
#539000
1%
#539500
0%
#540000
1%
1$
#540500
0%
#541000
1#
1%
#541500
0%
#542000
0#
1%
#542500
0%
0$
#543000
1#
1%
#543500
0%
#544000
b1000101 +
1%
#544500
0%
#545000
0#
1%
1$
#545500
0%
#546000
1#
1%
#546500
0%
#547000
1%
#547500
0%
0$
#548000
1%
#548500
0%
#549000
1%
#549500
0%
#550000
0#
1%
1$
#550500
0%
#551000
1%
#551500
0%
#552000
1#
b10111100 +
1%
#552500
0%
0$
#553000
0#
1%
#553500
0%
#554000
1#
1%
#554500
0%
#555000
1%
1$
#555500
0%
#556000
1%
#556500
0%
#557000
1%
#557500
0%
0$
#558000
0#
1%
#558500
0%
#559000
1%
#559500
0%
#560000
1#
1%
1$
#560500
0%
#561000
0#
1%
#561500
0%
#562000
1#
1%
#562500
0%
0$
#563000
1%
#563500
0%
#564000
1%
#564500
0%
#565000
1%
1$
#565500
0%
#566000
0#
1%
#566500
0%
#567000
1%
#567500
0%
0$
#568000
1#
1%
#568500
0%
#569000
0#
1%
#569500
0%
#570000
1#
1%
1$
#570500
0%
#571000
1%
#571500
0%
#572000
1%
#572500
0%
0$
#573000
1%
#573500
0%
#574000
0#
1%
#574500
0%
#575000
1%
1$
#575500
0%
#576000
1#
1%
#576500
0%
#577000
0#
1%
#577500
0%
0$
#578000
1#
1%
#578500
0%
#579000
0#
1%
#579500
0%
#580000
1#
1%
1$
#580500
0%
#581000
0#
1%
#581500
0%
#582000
1#
1%
#582500
0%
0$
#583000
0#
1%
#583500
0%
#584000
1#
b10101010 +
1%
#584500
0%
#585000
1%
1$
#585500
0%
#586000
1%
#586500
0%
#587000
0#
1%
#587500
0%
0$
#588000
1#
1%
#588500
0%
#589000
1%
#589500
0%
#590000
1%
1$
#590500
0%
#591000
0#
1%
#591500
0%
#592000
b11101110 +
1%
#592500
0%
0$
#593000
1%
#593500
0%
#594000
1%
#594500
0%
#595000
1#
1%
1$
#595500
0%
#596000
0#
1%
#596500
0%
#597000
1%
#597500
0%
0$
#598000
1#
1%
#598500
0%
#599000
1%
#599500
0%
#600000
b10011 +
1%
1$
#600500
0%
#601000
1%
#601500
0%
#602000
0#
1%
#602500
0%
0$
#603000
1%
#603500
0%
#604000
1#
1%
#604500
0%
#605000
1%
1$
#605500
0%
#606000
0#
1%
#606500
0%
#607000
1#
1%
#607500
0%
0$
#608000
b11001101 +
1%
#608500
0%
#609000
0#
1%
