phy_rx/logica_demuxes/probadorPrueba.v
module probadorPrueba (
		    output reg 	     clk_f,
		    output reg 	     clk_2f,
		    output reg 	     clk_4f,
			input  [7:0] 	 data_0,
		    input  [7:0] 	 data_1,
		    input  [7:0] 	 data_2,
		    input  [7:0] 	 data_3,
		    input 	     	 valid_0,
		    input 	     	 valid_1,
		    input  	     	 valid_2,
		    input  	     	 valid_3,
		    input [7:0]    data_00,
		    input  	     valid_00,
		    input  [7:0]    data_11,
		    input  	     valid_11,
		    output reg [7:0]     data_000,
		    output reg 	     	 valid_000);
	
   //Reloj

   initial clk_f <= 0;
   always #20 clk_f <= ~clk_f;
         
   //Reloj 2f

   initial clk_2f <= 1;
   always #10 clk_2f <= ~clk_2f;

   //Reloj 4f

   initial clk_4f <= 1;
   always #5 clk_4f <= ~clk_4f;
   

   // Secuencia de prueba

   initial
    begin
		$dumpfile ("senales_DEMUX_L1.vcd");
		$dumpvars;

		valid_000 = 1; //Valores iniciales de valids
		
		
		repeat (2) begin
		@(posedge clk_4f);
		{data_000} <= {8'hFF};
		
		

		@(posedge clk_4f);
		{data_000} <= {8'hDD};
		

		@(posedge clk_4f);
		{data_000} <= {8'hEE};
		
		

		@(posedge clk_4f);
		{data_000} <= {8'hCC};
		
		

		@(posedge clk_4f);
		{data_000} <= {8'hBB};
		


		@(posedge clk_4f);
		{data_000} <= {8'h99};


		@(posedge clk_4f);
		{data_000} <= {8'hAA};


		@(posedge clk_4f);
		{data_000} <= {8'h88};


		@(posedge clk_4f);
		{data_000} <= {8'h88};


		{valid_000} <= 0;


		@(posedge clk_4f);
		{data_000} <= {8'h77};

		{valid_000} <= 1;

		@(posedge clk_4f);
		{data_000} <= {8'h77};

		{valid_000} <= 0;
		

		end

		$finish;

     end // initial begin

endmodule //

phy_rx/DEMUX_L2.v
module DEMUX_L2 (
		input [7:0]         data_000,
        input 	            valid_000,
      	//input 		        clk_f,
      	input 		        clk_4f,
        input 		        clk_2f,
		output reg [7:0] 	data_00,
		output reg [7:0] 	data_11,
		output reg 		    valid_00,
		output reg 		    valid_11);

   //Señales internas
   reg [7:0] 	        a;
   reg [7:0]            b;
   //reg 	                selector_4f = 1;
   //reg                  selector_4f = 1;
   reg 	                validt_00;
   reg 	                validt_11;

   //Lógica selector automático

   /*always @ (posedge clk_4f)
        begin
	        selector_4f <= ~selector_4f;
        end
        
   always @ (posedge clk_4f)
        begin
	        selector_4f <= ~selector_4f;
        end*/

   //Lógica DEMUX 

   always @(posedge clk_4f)
     begin
	    /*validt_00 = (valid_000 & ~selector_4f) | (valid_000 & selector_4f);
        validt_11 = (valid_000 & ~selector_4f) | (valid_000 & selector_4f);*/     
        // a = 8'h00;
        // validt_00 = 1;

	    if (valid_000) begin
	        a <= data_000;
            validt_00 <= valid_000;
        end
	    else if (~valid_000) begin
            a <= a;
            validt_00 <= valid_000;
        end 
     end

    always @(negedge clk_4f) begin
        // b = 8'h00;
        // validt_11 = 1;
        if (valid_000) begin
	        b <= data_000;
            validt_11 <= valid_000;
        end
	    else if (~valid_000) begin
            b <= b;
            validt_11 <= valid_000;
        end 
    end
   // Lógica Flop

   always @ (posedge clk_2f)
    begin
	    if(validt_00)
	        begin
	            data_00 <= a;
	            valid_00 <= validt_00;
	        end
	    else
	        begin
                data_00 <= data_00;
                valid_00 <= validt_00;
	        end      
    end
   
   always @(posedge clk_2f) begin
       if(validt_11)
	        begin
                data_11 <= b;
                valid_11 <= validt_11;
	        end
	
	    else
	        begin
                data_11 <= data_11;
                valid_11 <= validt_11;
	        end
   end
	
endmodule // MUX_L2

phy_rx/DEMUX_L1.v
module DEMUX_L1 (
        input [7:0] data_00,
        input [7:0] data_11,
        input 		        valid_00,
        input 		        valid_11,
        input 		        clk_f,
      	input 		        clk_2f,
		output reg [7:0] 	data_0,
		output reg [7:0] 	data_1,
        output reg [7:0] 	data_2,
        output reg [7:0] 	data_3,
		output reg 		    valid_0,
		output reg 		    valid_1,
        output reg 		    valid_2,
		output reg 		    valid_3
        );

   //Señales internas
   reg [7:0] 	        c;
   reg [7:0]            d;
   reg [7:0] 	        e;
   reg [7:0]            f;
   
   reg 	                validt_0;
   reg 	                validt_1;
   reg 	                validt_2;
   reg 	                validt_3;

   //Lógica selector automático

   /*always @ (posedge clk_4f)
        begin
	        selector_4f <= ~selector_4f;
        end
        
   always @ (posedge clk_2f)
        begin
	        selector_2f <= ~selector_2f;
        end*/

   //Lógica DEMUX 

   always @(posedge clk_2f)
     begin
	    /*validt_00 = (valid_000 & ~selector_4f) | (valid_000 & selector_4f);
        validt_11 = (valid_000 & ~selector_4f) | (valid_000 & selector_4f);*/
        
        // data_11 = 8'h00;
        // data_00 = 8'h00;
        // validt_00 = 1;
        
        // validt_0 = 1;  
        // validt_1 = 1; 
        // validt_2 = 1; 
        // validt_3 = 1; 
        // c = 8'h00;
        // d = 8'h00;
        // e = 8'h00;
        // f = 8'h00;

	    
        if (valid_00) begin
	        f <= data_00;
            validt_2 <= valid_00;
        end
	    else if (~valid_00) begin
            f <= f;
            validt_2 <= valid_00;
        end 

         if (valid_11) begin
	        c <= data_11;
            validt_0 <= valid_11;
        end
	    else if (~valid_11) begin
            c <= c;
            validt_0 <= valid_11;
        end 
     end
      
      

    always @(negedge clk_2f) begin
       
         if (valid_00) begin
	        e <= data_11;
            validt_3 <= valid_00;
        end
	    else if (~valid_00) begin
            e <= e;
            validt_3 <= valid_00;
        end 
     
        if (valid_11) begin
	        d <= data_00;
            validt_1 <= valid_11;
        end
	    else if (~valid_11) begin
            d <= d;
            validt_1 <= valid_11;
        end 
    end

   // Lógica Flop

   always @ (posedge clk_f)
    begin

	    if(validt_0)
	        begin
	            data_0 <= c;
	            valid_0 <= validt_0;
	        end
	
	    else
	        begin
                data_0 <= data_0;
                valid_0 <= validt_0;
	        end      
    
        if(validt_1)
	        begin
                data_1 <= d;
                valid_1 <= validt_1;
	        end
	
	    else
	        begin
                data_1 <= data_1;
                valid_1 <= validt_1;
	        end

         if(validt_2)
	        begin
	            data_2 <= e;
	            valid_2 <= validt_2;
	        end
	
	    else
	        begin
                data_2 <= data_2;
                valid_2 <= validt_2;
	        end      
    
        if(validt_3)
	        begin
                data_3 <= f;
                valid_3 <= validt_3;
	        end
	
	    else
	        begin
                data_3 <= data_3;
                valid_3 <= validt_3;
	        end
    end
   
	
endmodule // DEMUX_L1

phy_rx/logica_demuxes/Banco_Pruebas.v
`timescale 1ns / 100ps

`include "DEMUX_L1.v"
`include "DEMUX_L2.v"
`include "probadorPrueba.v"



module Banco_pruebas;
   //Cables 
   /*AUTOWIRE*/
   // Beginning of automatic wires (for undeclared instantiated-module outputs)
   wire			clk_2f;			// From probadorPrueba of probadorPrueba.v
   wire			clk_4f;			// From probadorPrueba of probadorPrueba.v
   wire			clk_f;			// From probadorPrueba of probadorPrueba.v
   wire [7:0]		data_0;			// From DEMUX_L1 of DEMUX_L1.v
   wire [7:0]		data_00;		// From DEMUX_L2 of DEMUX_L2.v
   wire [7:0]		data_000;		// From probadorPrueba of probadorPrueba.v
   wire [7:0]		data_1;			// From DEMUX_L1 of DEMUX_L1.v
   wire [7:0]		data_11;		// From DEMUX_L2 of DEMUX_L2.v
   wire [7:0]		data_2;			// From DEMUX_L1 of DEMUX_L1.v
   wire [7:0]		data_3;			// From DEMUX_L1 of DEMUX_L1.v
   wire			valid_0;		// From DEMUX_L1 of DEMUX_L1.v
   wire			valid_00;		// From DEMUX_L2 of DEMUX_L2.v
   wire			valid_000;		// From probadorPrueba of probadorPrueba.v
   wire			valid_1;		// From DEMUX_L1 of DEMUX_L1.v
   wire			valid_11;		// From DEMUX_L2 of DEMUX_L2.v
   wire			valid_2;		// From DEMUX_L1 of DEMUX_L1.v
   wire			valid_3;		// From DEMUX_L1 of DEMUX_L1.v
   // End of automatics

   
   //Instancia DEMUX_L1 Conductual

   DEMUX_L1 DEMUX_L1(/*AUTOINST*/
		     // Outputs
		     .data_0		(data_0[7:0]),
		     .data_1		(data_1[7:0]),
		     .data_2		(data_2[7:0]),
		     .data_3		(data_3[7:0]),
		     .valid_0		(valid_0),
		     .valid_1		(valid_1),
		     .valid_2		(valid_2),
		     .valid_3		(valid_3),
		     // Inputs
		     .data_00		(data_00[7:0]),
		     .data_11		(data_11[7:0]),
		     .valid_00		(valid_00),
		     .valid_11		(valid_11),
		     .clk_f		(clk_f));

	//Instancia DEMUX_L2 Conductual

    DEMUX_L2 DEMUX_L2(/*AUTOINST*/
		      // Outputs
		      .data_00		(data_00[7:0]),
		      .data_11		(data_11[7:0]),
		      .valid_00		(valid_00),
		      .valid_11		(valid_11),
		      // Inputs
		      .data_000		(data_000[7:0]),
		      .valid_000	(valid_000),
		      .clk_2f		(clk_2f));
 
   //Instancia probador

   probadorPrueba probadorPrueba(/*AUTOINST*/
				 // Outputs
				 .clk_f			(clk_f),
				 .clk_2f		(clk_2f),
				 .clk_4f		(clk_4f),
				 .data_000		(data_000[7:0]),
				 .valid_000		(valid_000),
				 // Inputs
				 .data_0		(data_0[7:0]),
				 .data_1		(data_1[7:0]),
				 .data_2		(data_2[7:0]),
				 .data_3		(data_3[7:0]),
				 .valid_0		(valid_0),
				 .valid_1		(valid_1),
				 .valid_2		(valid_2),
				 .valid_3		(valid_3),
				 .data_00		(data_00[7:0]),
				 .valid_00		(valid_00),
				 .data_11		(data_11[7:0]),
				 .valid_11		(valid_11));
   

endmodule // Banco_pruebas

phy_rx/logica_demuxes/senales_DEMUX_L1.vcd
$date
	Tue Jun  8 20:03:16 2021
$end
$version
	Icarus Verilog
$end
$timescale
	100ps
$end
$scope module Banco_pruebas $end
$var wire 1 ! valid_3 $end
$var wire 1 " valid_2 $end
$var wire 1 # valid_11 $end
$var wire 1 $ valid_1 $end
$var wire 1 % valid_000 $end
$var wire 1 & valid_00 $end
$var wire 1 ' valid_0 $end
$var wire 8 ( data_3 [7:0] $end
$var wire 8 ) data_2 [7:0] $end
$var wire 8 * data_11 [7:0] $end
$var wire 8 + data_1 [7:0] $end
$var wire 8 , data_000 [7:0] $end
$var wire 8 - data_00 [7:0] $end
$var wire 8 . data_0 [7:0] $end
$var wire 1 / clk_f $end
$var wire 1 0 clk_4f $end
$var wire 1 1 clk_2f $end
$scope module DEMUX_L1 $end
$var wire 1 # valid_11 $end
$var wire 1 & valid_00 $end
$var wire 8 2 data_11 [7:0] $end
$var wire 8 3 data_00 [7:0] $end
$var wire 1 / clk_f $end
$var wire 1 1 clk_2f $end
$var reg 8 4 c [7:0] $end
$var reg 8 5 d [7:0] $end
$var reg 8 6 data_0 [7:0] $end
$var reg 8 7 data_1 [7:0] $end
$var reg 8 8 data_2 [7:0] $end
$var reg 8 9 data_3 [7:0] $end
$var reg 8 : e [7:0] $end
$var reg 8 ; f [7:0] $end
$var reg 1 ' valid_0 $end
$var reg 1 $ valid_1 $end
$var reg 1 " valid_2 $end
$var reg 1 ! valid_3 $end
$var reg 1 < validt_0 $end
$var reg 1 = validt_1 $end
$var reg 1 > validt_2 $end
$var reg 1 ? validt_3 $end
$upscope $end
$scope module DEMUX_L2 $end
$var wire 1 % valid_000 $end
$var wire 8 @ data_000 [7:0] $end
$var wire 1 0 clk_4f $end
$var wire 1 1 clk_2f $end
$var reg 8 A a [7:0] $end
$var reg 8 B b [7:0] $end
$var reg 8 C data_00 [7:0] $end
$var reg 8 D data_11 [7:0] $end
$var reg 1 & valid_00 $end
$var reg 1 # valid_11 $end
$var reg 1 E validt_00 $end
$var reg 1 F validt_11 $end
$upscope $end
$scope module probadorPrueba $end
$var wire 8 G data_0 [7:0] $end
$var wire 8 H data_00 [7:0] $end
$var wire 8 I data_1 [7:0] $end
$var wire 8 J data_11 [7:0] $end
$var wire 8 K data_2 [7:0] $end
$var wire 8 L data_3 [7:0] $end
$var wire 1 ' valid_0 $end
$var wire 1 & valid_00 $end
$var wire 1 $ valid_1 $end
$var wire 1 # valid_11 $end
$var wire 1 " valid_2 $end
$var wire 1 ! valid_3 $end
$var reg 1 1 clk_2f $end
$var reg 1 0 clk_4f $end
$var reg 1 / clk_f $end
$var reg 8 M data_000 [7:0] $end
$var reg 1 % valid_000 $end
$upscope $end
$upscope $end
$enddefinitions $end
#0
$dumpvars
b11111111 M
bx L
bx K
bx J
bx I
bx H
bx G
xF
1E
bx D
bx C
bx B
b11111111 A
b11111111 @
x?
x>
x=
x<
bx ;
bx :
bx 9
bx 8
bx 7
bx 6
bx 5
bx 4
bx 3
bx 2
11
10
0/
bx .
bx -
b11111111 ,
bx +
bx *
bx )
bx (
x'
x&
1%
x$
x#
x"
x!
$end
#50
1F
b11111111 B
00
#100
b11011101 ,
b11011101 @
b11011101 M
10
01
#150
b11011101 B
00
#200
b11011101 A
b11101110 ,
b11101110 @
b11101110 M
1#
b11011101 *
b11011101 2
b11011101 D
b11011101 J
1&
b11111111 -
b11111111 3
b11111111 C
b11111111 H
10
11
1/
#250
b11101110 B
00
#300
b11001100 ,
b11001100 @
b11001100 M
b11101110 A
1=
b11111111 :
1?
b11011101 ;
10
01
#350
b11001100 B
00
#400
b11001100 A
b10111011 ,
b10111011 @
b10111011 M
1<
b11011101 5
1>
b11111111 4
b11101110 -
b11101110 3
b11101110 C
b11101110 H
b11001100 *
b11001100 2
b11001100 D
b11001100 J
10
11
0/
#450
b10111011 B
00
#500
b10011001 ,
b10011001 @
b10011001 M
b10111011 A
b11101110 :
b11001100 ;
10
01
#550
b10011001 B
00
#600
b10011001 A
b10101010 ,
b10101010 @
b10101010 M
b10011001 *
b10011001 2
b10011001 D
b10011001 J
b10111011 -
b10111011 3
b10111011 C
b10111011 H
b11001100 5
b11101110 4
1!
b11001100 (
b11001100 9
b11001100 L
1"
b11101110 )
b11101110 8
b11101110 K
1$
b11011101 +
b11011101 7
b11011101 I
1'
b11111111 .
b11111111 6
b11111111 G
10
11
1/
#650
b10101010 B
00
#700
b10001000 ,
b10001000 @
b10001000 M
b10101010 A
b10111011 :
b10011001 ;
10
01
#750
b10001000 B
00
#800
b10001000 A
0%
b10011001 5
b10111011 4
b10101010 -
b10101010 3
b10101010 C
b10101010 H
b10001000 *
b10001000 2
b10001000 D
b10001000 J
10
11
0/
#850
0F
00
#900
1%
b1110111 ,
b1110111 @
b1110111 M
0E
b10101010 :
b10001000 ;
10
01
#950
1F
b1110111 B
00
#1000
1E
b1110111 A
0%
b1110111 *
b1110111 2
b1110111 D
b1110111 J
0&
b10001000 5
b10101010 4
b10001000 (
b10001000 9
b10001000 L
b10101010 )
b10101010 8
b10101010 K
b10011001 +
b10011001 7
b10011001 I
b10111011 .
b10111011 6
b10111011 G
10
11
1/
#1050
0F
00
#1100
0E
0?
10
01
#1150
00
#1200
b11011101 ,
b11011101 @
b11011101 M
b1110111 5
0>
0#
10
11
0/
#1250
00
#1300
b11101110 ,
b11101110 @
b11101110 M
0=
10
01
#1350
00
#1400
b11001100 ,
b11001100 @
b11001100 M
0<
0!
0"
0$
b10101010 .
b10101010 6
b10101010 G
10
11
1/
#1450
00
#1500
b10111011 ,
b10111011 @
b10111011 M
10
01
#1550
00
#1600
b10011001 ,
b10011001 @
b10011001 M
10
11
0/
#1650
00
#1700
b10101010 ,
b10101010 @
b10101010 M
10
01
#1750
00
#1800
b10001000 ,
b10001000 @
b10001000 M
0'
10
11
1/
#1850
00
#1900
10
01
#1950
00
#2000
1%
b1110111 ,
b1110111 @
b1110111 M
10
11
0/
#2050
1F
00
#2100
0%
1E
10
01
